[
  {
    "id": "edit_table_modal_select_title",
    "en": "Select source",
    "fr": "",
    "es": "",
    "ru": "",
    "zh": "",
    "ar": "",
    "fa": "",
    "ps": "",
    "bn": "",
    "de": ""
  },
  {
    "id": "edit_table_modal_select_label",
    "en": "Select source to edit",
    "fr": "",
    "es": "",
    "ru": "",
    "zh": "",
    "ar": "",
    "fa": "",
    "ps": "",
    "bn": "",
    "de": ""
  },
  {
    "id": "edit_table_modal_title",
    "en": "Edit source {{title}}",
    "fr": "",
    "es": "",
    "ru": "",
    "zh": "",
    "ar": "",
    "fa": "",
    "ps": "",
    "bn": "",
    "de": ""
  },
  {
    "id": "btn_edit_geom_validate",
    "en": "Validate the geometry",
    "fr": "",
    "es": "",
    "ru": "",
    "zh": "",
    "ar": "",
    "fa": "",
    "ps": "",
    "bn": "",
    "de": ""
  },
  {
    "id": "btn_edit_geom_repair",
    "en": "Repair the geometry",
    "fr": "",
    "es": "",
    "ru": "",
    "zh": "",
    "ar": "",
    "fa": "",
    "ps": "",
    "bn": "",
    "de": ""
  },
  {
    "id": "btn_edit_menu_tools",
    "en": "Tools...",
    "fr": "",
    "es": "",
    "ru": "",
    "zh": "",
    "ar": "",
    "fa": "",
    "ps": "",
    "bn": "",
    "de": ""
  },
  {
    "id": "btn_edit_undo",
    "en": "Undo",
    "fr": "",
    "es": "",
    "ru": "",
    "zh": "",
    "ar": "",
    "fa": "",
    "ps": "",
    "bn": "",
    "de": ""
  },
  {
    "id": "btn_edit_undo_last",
    "en": "Undo last change",
    "fr": "",
    "es": "",
    "ru": "",
    "zh": "",
    "ar": "",
    "fa": "",
    "ps": "",
    "bn": "",
    "de": ""
  },
  {
    "id": "btn_edit_redo",
    "en": "Redo",
    "fr": "",
    "es": "",
    "ru": "",
    "zh": "",
    "ar": "",
    "fa": "",
    "ps": "",
    "bn": "",
    "de": ""
  },
  {
    "id": "edit_table_modal_values_invalid_title",
    "en": "Invalid values",
    "fr": "",
    "es": "",
    "ru": "",
    "zh": "",
    "ar": "",
    "fa": "",
    "ps": "",
    "bn": "",
    "de": ""
  },
  {
    "id": "edit_table_modal_values_invalid_ok",
    "en": "Ok",
    "fr": "",
    "es": "",
    "ru": "",
    "zh": "",
    "ar": "",
    "fa": "",
    "ps": "",
    "bn": "",
    "de": ""
  },
  {
    "id": "btn_edit_add_column",
    "en": "Add column",
    "fr": "",
    "es": "",
    "ru": "",
    "zh": "",
    "ar": "",
    "fa": "",
    "ps": "",
    "bn": "",
    "de": ""
  },
  {
    "id": "btn_edit_remove_column",
    "en": "Remove column",
    "fr": "",
    "es": "",
    "ru": "",
    "zh": "",
    "ar": "",
    "fa": "",
    "ps": "",
    "bn": "",
    "de": ""
  },
  {
    "id": "btn_edit_autosave_label",
    "en": "Auto save",
    "fr": "",
    "es": "",
    "ru": "",
    "zh": "",
    "ar": "",
    "fa": "",
    "ps": "",
    "bn": "",
    "de": ""
  },
  {
    "id": "btn_edit_autosave_desc",
    "en": "Automatically update the table and stream changes among other users as appropriate. If disabled, only you will be able to make changes to this table, and the table will be locked for others.",
    "fr": "",
    "es": "",
    "ru": "",
    "zh": "",
    "ar": "",
    "fa": "",
    "ps": "",
    "bn": "",
    "de": ""
  },

  {
    "id": "edit_table_modal_add_column_type_title",
    "en": "Add a new column column : type ",
    "fr": "",
    "es": "",
    "ru": "",
    "zh": "",
    "ar": "",
    "fa": "",
    "ps": "",
    "bn": "",
    "de": ""
  },
  {
    "id": "edit_table_modal_add_column_name_title",
    "en": "Name of the column",
    "fr": "",
    "es": "",
    "ru": "",
    "zh": "",
    "ar": "",
    "fa": "",
    "ps": "",
    "bn": "",
    "de": ""
  },
  {
    "id": "edit_table_modal_add_column_name_label",
    "en": "Column name",
    "fr": "",
    "es": "",
    "ru": "",
    "zh": "",
    "ar": "",
    "fa": "",
    "ps": "",
    "bn": "",
    "de": ""
  },
  {
    "id": "edit_table_modal_add_column_name_template",
    "en": "The column name will be: <code>{{column_name}}</code>",
    "fr": "",
    "es": "",
    "ru": "",
    "zh": "",
    "ar": "",
    "fa": "",
    "ps": "",
    "bn": "",
    "de": ""
  },
  {
    "id": "edit_table_modal_add_column_name_issue_length",
    "en": "Length should be more than {{minLength}} and less than {{maxLength}} characters",
    "fr": "",
    "es": "",
    "ru": "",
    "zh": "",
    "ar": "",
    "fa": "",
    "ps": "",
    "bn": "",
    "de": ""
  },
  {
    "id": "edit_table_modal_add_column_name_issue_invalid_characters",
    "en": "Name can't start with a number, contain spaces or any special characters, or use reserved keywords",
    "fr": "",
    "es": "",
    "ru": "",
    "zh": "",
    "ar": "",
    "fa": "",
    "ps": "",
    "bn": "",
    "de": ""
  },
  {
    "id": "edit_table_modal_add_column_name_issue_non_available",
    "en": "Name unavailable",
    "fr": "",
    "es": "",
    "ru": "",
    "zh": "",
    "ar": "",
    "fa": "",
    "ps": "",
    "bn": "",
    "de": ""
  },
  {
    "id": "edit_table_modal_add_column_type_label",
    "en": "Select data type",
    "fr": "",
    "es": "",
    "ru": "",
    "zh": "",
    "ar": "",
    "fa": "",
    "ps": "",
    "bn": "",
    "de": ""
  },
  {
    "id": "edit_table_modal_add_column_confirm_title",
    "en": "Add a new column : confirm",
    "fr": "",
    "es": "",
    "ru": "",
    "zh": "",
    "ar": "",
    "fa": "",
    "ps": "",
    "bn": "",
    "de": ""
  },
  {
    "id": "edit_table_modal_add_column_confirm_text",
    "en": "Add a new column named <code>{{column_name}}</code> of type <code>{{column_type}}</code> ? Change will be done in the database and all interactive tables. This can't be undone, but the tool 'Remove a column' will work, if required. ",
    "fr": "",
    "es": "",
    "ru": "",
    "zh": "",
    "ar": "",
    "fa": "",
    "ps": "",
    "bn": "",
    "de": ""
  },
  {
    "id": "btn_edit_table_modal_add_column_confirm",
    "en": "Add the column",
    "fr": "",
    "es": "",
    "ru": "",
    "zh": "",
    "ar": "",
    "fa": "",
    "ps": "",
    "bn": "",
    "de": ""
  },
  {
    "id": "edit_table_modal_remove_column_title",
    "en": "Remove a column : selection",
    "fr": "",
    "es": "",
    "ru": "",
    "zh": "",
    "ar": "",
    "fa": "",
    "ps": "",
    "bn": "",
    "de": ""
  },
  {
    "id": "edit_table_modal_remove_column_label",
    "en": "Column name",
    "fr": "",
    "es": "",
    "ru": "",
    "zh": "",
    "ar": "",
    "fa": "",
    "ps": "",
    "bn": "",
    "de": ""
  },
  {
    "id": "edit_table_modal_remove_column_confirm_title",
    "en": "Remove a column : confirm",
    "fr": "",
    "es": "",
    "ru": "",
    "zh": "",
    "ar": "",
    "fa": "",
    "ps": "",
    "bn": "",
    "de": ""
  },
  {
    "id": "edit_table_modal_remove_column_confirm_text",
    "en": "Remove a column named <code>{{column_name}}</code> ? Change will be done in the database and all interactive tables. This can't be undone: data can be lost.",
    "fr": "",
    "es": "",
    "ru": "",
    "zh": "",
    "ar": "",
    "fa": "",
    "ps": "",
    "bn": "",
    "de": ""
  },
  {
    "id": "btn_edit_table_modal_remove_column_confirm",
    "en": "Remove the column",
    "fr": "",
    "es": "",
    "ru": "",
    "zh": "",
    "ar": "",
    "fa": "",
    "ps": "",
    "bn": "",
    "de": ""
  },
  {
    "id": "edit_table_users_stat",
    "en": "Users currently editing this table: ",
    "fr": "",
    "es": "",
    "ru": "",
    "zh": "",
    "ar": "",
    "fa": "",
    "ps": "",
    "bn": "",
    "de": ""
  },

  {
    "id": "edit_table_modal_large_changes_number_title",
    "en": "Large number of change detected",
    "fr": "",
    "es": "",
    "ru": "",
    "zh": "",
    "ar": "",
    "fa": "",
    "ps": "",
    "bn": "",
    "de": ""
  },
  {
    "id": "edit_table_modal_large_changes_number_content",
    "en": "Large number of changes detected: {{count}}. Do you want to proceed anyway? Operations could be delayed",
    "fr": "",
    "es": "",
    "ru": "",
    "zh": "",
    "ar": "",
    "fa": "",
    "ps": "",
    "bn": "",
    "de": ""
  },
  {
    "id": "btn_edit_table_modal_large_changes_number_continue",
    "en": "Yes, continue",
    "fr": "",
    "es": "",
    "ru": "",
    "zh": "",
    "ar": "",
    "fa": "",
    "ps": "",
    "bn": "",
    "de": ""
  },
  {
    "id": "btn_edit_table_modal_large_changes_number_undo",
    "en": "No, undo last action",
    "fr": "",
    "es": "",
    "ru": "",
    "zh": "",
    "ar": "",
    "fa": "",
    "ps": "",
    "bn": "",
    "de": ""
  },
  {
    "id": "edit_table_modal_warning_title",
    "en": "Edition warning",
    "fr": "",
    "es": "",
    "ru": "",
    "zh": "",
    "ar": "",
    "fa": "",
    "ps": "",
    "bn": "",
    "de": ""
  },
  {
    "id": "edit_table_modal_warning_text",
    "en": "<ul><li>Using this tool may pose a risk of permanently altering or deleting data, similar to desktop spreadsheet editors.</li><li>It is possible to undo or redo any changes made to cells during a session using keyboard shortcuts or dedicated buttons.</li><li>The &#39;Remove column&#39; action will permanently delete the column and its data, and cannot be undone after the final confirmation panel.</li><li>Invalid cells, indicated by a red color, will not be saved.</li><li>A backup system has not yet been implemented. To safeguard your data, you can use the download tool in the toolbox to export the entire layer or table as a precautionary measure.</li><li>There may be incremental backup at the database level, but not at the layer or table level.</li><li>The developers of the current platform and project administrators do not accept any responsibility for any potential losses or damages.</li></ul>",
    "fr": "",
    "es": "",
    "ru": "",
    "zh": "",
    "ar": "",
    "fa": "",
    "ps": "",
    "bn": "",
    "de": ""
  },
  {
    "id": "edit_table_modal_warning_ok_no_more",
    "en": "I understand, don't remind me this",
    "fr": "",
    "es": "",
    "ru": "",
    "zh": "",
    "ar": "",
    "fa": "",
    "ps": "",
    "bn": "",
    "de": ""
  },
  {
    "id": "edit_table_modal_warning_ok",
    "en": "I understand",
    "fr": "",
    "es": "",
    "ru": "",
    "zh": "",
    "ar": "",
    "fa": "",
    "ps": "",
    "bn": "",
    "de": ""
  },
  {
    "id": "edit_table_modal_help",
    "en": "Table editor help",
    "fr": "",
    "es": "",
    "ru": "",
    "zh": "",
    "ar": "",
    "fa": "",
    "ps": "",
    "bn": "",
    "de": ""
  },
  {
    "id": "edit_table_modal_changes_too_big_title",
    "en": "Too much changes at once",
    "fr": "",
    "es": "",
    "ru": "",
    "zh": "",
    "ar": "",
    "fa": "",
    "ps": "",
    "bn": "",
    "de": ""
  },
  {
    "id": "edit_table_modal_changes_too_big_content",
    "en": "Last action did produce {{count}} changes. The maximum allowed changes at once is {{max_changes}}. Last edit was canceled.",
    "fr": "",
    "es": "",
    "ru": "",
    "zh": "",
    "ar": "",
    "fa": "",
    "ps": "",
    "bn": "",
    "de": ""
  },
  {
    "id": "btn_edit_table_modal_changes_too_big_ok",
    "en": "ok",
    "fr": "",
    "es": "",
    "ru": "",
    "zh": "",
    "ar": "",
    "fa": "",
    "ps": "",
    "bn": "",
    "de": ""
  },
  {
    "id": "edit_table_modal_columns_name_issue_title",
    "en": "Invalid column names",
    "fr": "",
    "es": "",
    "ru": "",
    "zh": "",
    "ar": "",
    "fa": "",
    "ps": "",
    "bn": "",
    "de": ""
  },
  {
    "id": "edit_table_modal_columns_name_issue_content",
    "en": "Some column(s) contain invalid characters and cannot be edited: <ul> {{columns}} </ul>",
    "fr": "",
    "es": "",
    "ru": "",
    "zh": "",
    "ar": "",
    "fa": "",
    "ps": "",
    "bn": "",
    "de": ""
  },
  {
    "id": "edit_table_modal_attributes_title",
    "en": "Attribute table",
    "fr": "Table attributaire",
    "es": "Tabla de atributos",
    "ru": "",
    "zh": "属性表",
    "ar": "",
    "fa": "",
    "ps": "",
    "bn": "",
    "de": ""
  },
  {
    "id": "btn_edit_table_modal_clear_filter",
    "en": "Reset filters",
    "fr": "",
    "es": "",
    "ru": "",
    "zh": "",
    "ar": "",
    "fa": "",
    "ps": "",
    "bn": "",
    "de": ""
  },
  {
    "id": "btn_edit_table_modal_edit",
    "en": "Edit",
    "fr": "",
    "es": "",
    "ru": "",
    "zh": "",
    "ar": "",
    "fa": "",
    "ps": "",
    "bn": "",
    "de": ""
  },
  {
    "id": "btn_edit_table_modal_export_csv",
    "en": "Export CSV",
    "fr": "",
    "es": "",
    "ru": "",
    "zh": "",
    "ar": "",
    "fa": "",
    "ps": "",
    "bn": "",
    "de": ""
  },
  {
    "id": "edit_table_modal_data_init",
    "en": "Initializing, please wait...",
    "fr": "",
    "es": "",
    "ru": "",
    "zh": "",
    "ar": "",
    "fa": "",
    "ps": "",
    "bn": "",
    "de": ""
  },
  {
    "id": "edit_table_modal_data_fetch",
    "en": "Download data...",
    "fr": "",
    "es": "",
    "ru": "",
    "zh": "",
    "ar": "",
    "fa": "",
    "ps": "",
    "bn": "",
    "de": ""
  },
  {
    "id": "edit_table_modal_data_ok_build",
    "en": "Data downloaded, build table.",
    "fr": "",
    "es": "",
    "ru": "",
    "zh": "",
    "ar": "",
    "fa": "",
    "ps": "",
    "bn": "",
    "de": ""
  },
  {
    "id": "edit_table_modal_validate_title",
    "en": "Validate geometries",
    "fr": "",
    "es": "",
    "ru": "",
    "zh": "",
    "ar": "",
    "fa": "",
    "ps": "",
    "bn": "",
    "de": ""
  },
  {
    "id": "edit_table_modal_validate_desc",
    "en": "This tool will revalidate all geometries and mark invalid ones as such.",
    "fr": "",
    "es": "",
    "ru": "",
    "zh": "",
    "ar": "",
    "fa": "",
    "ps": "",
    "bn": "",
    "de": ""
  },
  {
    "id": "edit_table_modal_repair_title",
    "en": "Repair invalid geometries",
    "fr": "",
    "es": "",
    "ru": "",
    "zh": "",
    "ar": "",
    "fa": "",
    "ps": "",
    "bn": "",
    "de": ""
  },
  {
    "id": "edit_table_modal_repair_desc",
    "en": "This tool repair invalid geometries reported by the validation tool. Invalid geometries are geometries that contain for example self-intersecting polygons. Please read the wiki for more information.",
    "fr": "Cet outil va corriger les géométries invalides rapportée par l'outil de validation. Les géométries invalides sont des géométries qui contiennent par exemple des polygones auto-sécants. Veuillez consulter le wiki pour plus d'informations.",
    "es": "",
    "ru": "",
    "zh": "",
    "ar": "",
    "fa": "",
    "ps": "",
    "bn": "",
    "de": ""
  },
  {
    "id": "edit_table_modal_quit_ignore_changes_title",
    "en": "Unsaved changes",
    "fr": "",
    "es": "",
    "ru": "",
    "zh": "",
    "ar": "",
    "fa": "",
    "ps": "",
    "bn": "",
    "de": ""
  },
  {
    "id": "edit_table_modal_quit_ignore_changes",
    "en": "This table has {{count}} unsaved changes. Are you sure you want to quit and discard those changes ?",
    "fr": "",
    "es": "",
    "ru": "",
    "zh": "",
    "ar": "",
    "fa": "",
    "ps": "",
    "bn": "",
    "de": ""
  },
  {
    "id": "edit_table_modal_issue_name_is_not_used",
    "en": "in use",
    "fr": "",
    "es": "",
    "ru": "",
    "zh": "",
    "ar": "",
    "fa": "",
    "ps": "",
    "bn": "",
    "de": ""
  },
  {
    "id": "edit_table_modal_issue_name_is_not_reserved",
    "en": "reserved",
    "fr": "",
    "es": "",
    "ru": "",
    "zh": "",
    "ar": "",
    "fa": "",
    "ps": "",
    "bn": "",
    "de": ""
  },
  {
    "id": "edit_table_modal_issue_name_is_safe",
    "en": "not safe",
    "fr": "",
    "es": "",
    "ru": "",
    "zh": "",
    "ar": "",
    "fa": "",
    "ps": "",
    "bn": "",
    "de": ""
  },
  {
    "id": "edit_table_modal_rename_column_title",
    "en": "Rename column",
    "fr": "",
    "es": "",
    "ru": "",
    "zh": "",
    "ar": "",
    "fa": "",
    "ps": "",
    "bn": "",
    "de": ""
  },
  {
    "id": "edit_table_modal_rename_column_label",
    "en": "Choose the column you want to rename:",
    "fr": "",
    "es": "",
    "ru": "",
    "zh": "",
    "ar": "",
    "fa": "",
    "ps": "",
    "bn": "",
    "de": ""
  },
  {
    "id": "edit_table_modal_rename_column_confirm_title",
    "en": "Confirmation",
    "fr": "",
    "es": "",
    "ru": "",
    "zh": "",
    "ar": "",
    "fa": "",
    "ps": "",
    "bn": "",
    "de": ""
  },
  {
    "id": "edit_table_modal_rename_column_confirm_text",
    "en": "Are you sure you want to rename the column <code>{{column_name}}</code> to <code>{{column_name_new}}</code>?<br> Objects and dependencies stored in the DB will be updated seamlessly, but custom scripts such as those used in dashboards, custom styles, or hardcoded SQL queries should be updated manually.",
    "fr": "Êtes-vous sûr de vouloir renommer la colonne <code>{{column_name}}</code> en <code>{{column_name_new}}</code> ?<br> Les objets et dépendances stockés dans la base de données seront mis à jour automatiquement, mais les scripts personnalisés tels que ceux utilisés dans les tableaux de bord, les styles personnalisés ou les requêtes SQL codées en dur doivent être mis à jour manuellement.",
    "es": "¿Estás seguro de que deseas renombrar la columna <code>{{column_name}}</code> a <code>{{column_name_new}}</code>?<br> Los objetos y dependencias almacenados en la base de datos se actualizarán de forma transparente, pero los scripts personalizados, como los utilizados en paneles de control, estilos personalizados o consultas SQL codificadas directamente, deben actualizarse manualmente.",
    "ru": "Вы уверены, что хотите переименовать столбец <code>{{column_name}}</code> в <code>{{column_name_new}}</code>?<br> Объекты и зависимости, хранящиеся в базе данных, будут обновлены автоматически, но пользовательские скрипты, такие как используемые в панелях мониторинга, пользовательские стили или жестко закодированные SQL-запросы, должны быть обновлены вручную.",
    "zh": "您确定要将列 <code>{{column_name}}</code> 重命名为 <code>{{column_name_new}}</code> 吗？<br> 存储在数据库中的对象和依赖项将无缝更新，但是自定义脚本，如仪表板中使用的脚本、自定义样式或硬编码的 SQL 查询，需要手动更新。",
    "ar": "هل أنت متأكد أنك تريد إعادة تسمية العمود <code>{{column_name}}</code> إلى <code>{{column_name_new}}</code>؟<br> سيتم تحديث الكائنات والتبعيات المخزنة في قاعدة البيانات بسلاسة، ولكن يجب تحديث السكريبتات المخصصة مثل تلك المستخدمة في لوحات المعلومات، الأنماط المخصصة، أو الاستعلامات SQL المكتوبة بشكل صلب يدويًا.",
    "fa": "آیا مطمئن هستید که می‌خواهید ستون <code>{{column_name}}</code> را به <code>{{column_name_new}}</code> تغییر نام دهید؟<br> اشیاء و وابستگی‌های ذخیره‌شده در پایگاه داده به طور خودکار به‌روزرسانی می‌شوند، اما اسکریپت‌های سفارشی مانند آنهایی که در داشبوردها، سبک‌های سفارشی، یا پرس‌وجوهای SQL سخت‌کد شده استفاده می‌شوند، باید به صورت دستی به‌روزرسانی شوند.",
    "ps": "آیا تاسو ډاډه یاست چې غواړئ کالم <code>{{column_name}}</code> بیا نومول <code>{{column_name_new}}</code> ته؟<br> په ډیټابیس کې ذخیره شوي اشیا او تکیه ځایونه به په بې ساري ډول تازه شي، خو د دشبورډونو، دودیزو سټایلونو، یا سخت کوډ شوي SQL پوښتنو په څیر دودیز سکریپټونه باید په لاسي ډول تازه شي.",
    "bn": "আপনি কি নিশ্চিত যে আপনি কলাম <code>{{column_name}}</code> এর নাম পরিবর্তন করে <code>{{column_name_new}}</code> করতে চান?<br> ডাটাবেসে সংরক্ষিত অবজেক্ট এবং নির্ভরতা সমূহ সহজে আপডেট হবে, তবে ড্যাশবোর্ডে ব্যবহৃত, কাস্টম স্টাইল বা হার্ডকোডেড SQL কোয়েরির মতো কাস্টম স্ক্রিপ্টগুলি ম্যানুয়ালি আপডেট করতে হবে।",
    "de": "Sind Sie sicher, dass Sie die Spalte <code>{{column_name}}</code> in <code>{{column_name_new}}</code> umbenennen möchten?<br> Objekte und Abhängigkeiten in der DB werden nahtlos aktualisiert, aber benutzerdefinierte Skripte, wie sie in Dashboards, benutzerdefinierten Stilen oder hartkodierten SQL-Abfragen verwendet werden, müssen manuell aktualisiert werden."
  },
  {
    "id": "btn_edit_rename_column",
    "en": "Rename column",
    "fr": "",
    "es": "",
    "ru": "",
    "zh": "",
    "ar": "",
    "fa": "",
    "ps": "",
    "bn": "",
    "de": ""
  },
  {
    "id": "btn_edit_table_modal_rename_column_confirm",
    "en": "Rename column",
    "fr": "",
    "es": "",
    "ru": "",
    "zh": "",
    "ar": "",
    "fa": "",
    "ps": "",
    "bn": "",
    "de": ""
  },
  {
    "id": "edit_table_modal_has_code_title",
    "en": "Existing references in code",
    "fr": "",
    "es": "",
    "ru": "",
    "zh": "",
    "ar": "",
    "fa": "",
    "ps": "",
    "bn": "",
    "de": ""
  },
  {
    "id": "edit_table_modal_has_code",
    "en": "<p>Column renaming is not allowed since this table is referenced in custom code views, dashboards, and / or custom styles. If required, consider duplicating the column instead.<br><br>For more details, click the 'Help' button.<br><br>Here is the list of dependent views:</p>",
    "fr": "",
    "es": "",
    "ru": "",
    "zh": "",
    "ar": "",
    "fa": "",
    "ps": "",
    "bn": "",
    "de": ""
  },
  {
    "id": "edit_table_modal_has_code_close",
    "en": "Cancel",
    "fr": "",
    "es": "",
    "ru": "",
    "zh": "",
    "ar": "",
    "fa": "",
    "ps": "",
    "bn": "",
    "de": ""
  },
  {
    "id": "edit_table_view_with_dashboard",
    "en": "Dashboard",
    "fr": "",
    "es": "",
    "ru": "",
    "zh": "",
    "ar": "",
    "fa": "",
    "ps": "",
    "bn": "",
    "de": ""
  },
  {
    "id": "edit_table_view_with_custom_code",
    "en": "Custom Code",
    "fr": "",
    "es": "",
    "ru": "",
    "zh": "",
    "ar": "",
    "fa": "",
    "ps": "",
    "bn": "",
    "de": ""
  },
  {
    "id": "edit_table_view_with_custom_style",
    "en": "Custom style",
    "fr": "",
    "es": "",
    "ru": "",
    "zh": "",
    "ar": "",
    "fa": "",
    "ps": "",
    "bn": "",
    "de": ""
  },
  {
    "id": "edit_table_view_with_layer",
    "en": "Source layer",
    "fr": "",
    "es": "",
    "ru": "",
    "zh": "",
    "ar": "",
    "fa": "",
    "ps": "",
    "bn": "",
    "de": ""
  },
  {
    "id": "btn_edit_duplicate_column",
    "en": "Duplicate column",
    "fr": "",
    "es": "",
    "ru": "",
    "zh": "",
    "ar": "",
    "fa": "",
    "ps": "",
    "bn": "",
    "de": ""
  },
  {
    "id": "edit_table_modal_duplicate_column_title",
    "en": "Duplicate column",
    "fr": "",
    "es": "",
    "ru": "",
    "zh": "",
    "ar": "",
    "fa": "",
    "ps": "",
    "bn": "",
    "de": ""
  },
  {
    "id": "edit_table_modal_duplicate_column_label",
    "en": "Column to duplicate",
    "fr": "",
    "es": "",
    "ru": "",
    "zh": "",
    "ar": "",
    "fa": "",
    "ps": "",
    "bn": "",
    "de": ""
  },
  {
    "id": "edit_table_modal_duplicate_column_confirm_title",
    "en": "Column to duplicate : confirm",
    "fr": "",
    "es": "",
    "ru": "",
    "zh": "",
    "ar": "",
    "fa": "",
    "ps": "",
    "bn": "",
    "de": ""
  },
  {
    "id": "edit_table_modal_duplicate_column_confirm_text",
    "en": "Duplicate the column named <code>{{column_name}}</code> to a new column named <code>{{column_name_new}}</code> ?",
    "fr": "",
    "es": "",
    "ru": "",
    "zh": "",
    "ar": "",
    "fa": "",
    "ps": "",
    "bn": "",
    "de": ""
  },
  {
    "id": "btn_edit_table_modal_duplicate_column_confirm",
    "en": "Duplicate the column",
    "fr": "",
    "es": "",
    "ru": "",
    "zh": "",
    "ar": "",
    "fa": "",
    "ps": "",
    "bn": "",
    "de": ""
  },
  {
    "id": "btn_stat_attribute",
    "en": "Statistics",
    "fr": "",
    "es": "",
    "ru": "",
    "zh": "",
    "ar": "",
    "fa": "",
    "ps": "",
    "bn": "",
    "de": ""
  },
  {
    "id": "edit_table_modal_stat_column_title",
    "en": "Attribute for statistics",
    "fr": "",
    "es": "",
    "ru": "",
    "zh": "",
    "ar": "",
    "fa": "",
    "ps": "",
    "bn": "",
    "de": ""
  },
  {
    "id": "edit_table_modal_stat_column_label",
    "en": "Select an attribute",
    "fr": "",
    "es": "",
    "ru": "",
    "zh": "",
    "ar": "",
    "fa": "",
    "ps": "",
    "bn": "",
    "de": ""
  },
  {
    "id": "edit_table_modal_order_columns_modified_title",
    "en": "Columns order modified",
    "fr": "",
    "es": "",
    "ru": "",
    "zh": "",
    "ar": "",
    "fa": "",
    "ps": "",
    "bn": "",
    "de": ""
  },
  {
    "id": "edit_table_modal_order_columns_modified_text",
    "en": "Columns order has been modified by another user.",
    "fr": "",
    "es": "",
    "ru": "",
    "zh": "",
    "ar": "",
    "fa": "",
    "ps": "",
    "bn": "",
    "de": ""
  },
  {
    "id": "btn_edit_table_modal_order_columns_modified_ok",
    "en": "ok",
    "fr": "",
    "es": "",
    "ru": "",
    "zh": "",
    "ar": "",
    "fa": "",
    "ps": "",
    "bn": "",
    "de": ""
  },
  {
    "id": "btn_edit_columns_order",
    "en": "Set columns order",
    "fr": "",
    "es": "",
    "ru": "",
    "zh": "",
    "ar": "",
    "fa": "",
    "ps": "",
    "bn": "",
    "de": ""
  },
  {
    "id": "edit_table_modal_order_columns_title",
    "en": "Set columns order",
    "fr": "",
    "es": "",
    "ru": "",
    "zh": "",
    "ar": "",
    "fa": "",
    "ps": "",
    "bn": "",
    "de": ""
  }
]
