{
  "getApiSql": "/get/sql",
  "getSearchKey": "/get/search/key",
  "getIpInfo": "/get/ip",
  "getMirror": "/get/mirror",
  "getConfigMap": "/get/config/map",
  "getTile": "/get/tile/{x}/{y}/{z}.mvt",
  "getSourceMetadata": "/get/source/metadata/",
  "getSourceSummary": "/get/source/summary/",
  "getViewMetadata": "/get/view/metadata/",
  "getViewSourceMetadata": "/get/view/source/metadata/",
  "getSourceOverlap": "/get/source/overlap/",
  "getSourceValidateGeom": "/get/source/validate/geom",
  "getSourceTableAttribute": "/get/source/table/attribute",
  "getView": "/get/view/item/",
  "getViewsListByProject": "/get/views/list/project/",
  "getViewsListGlobalPublic": "/get/views/list/global/public",
  "getProjectsListByUser": "/get/projects/list/user",
  "getSourceDownload": "/get/source/",
  "getFileFormatsList": "/get/file/formats/list",
  "getEpsgCodesFull": "/get/epsg/codes/full",
  "uploadImage": "/upload/image/",
  "uploadVector": "/upload/vector/",
  "postEmail": "/send/mail",
  "collectLogs": "/collect/logs/"
}
