[
  {
    "id": "admin",
    "en": "Administrator",
    "ru": ""
  },
  {
    "id": "admins",
    "en": "Administrators",
    "ru": ""
  },
  {
    "id": "bottom",
    "en": "Bottom",
    "ru": ""
  },
  {
    "id": "btn_browse",
    "en": "Browse...",
    "ru": ""
  },
  {
    "id": "btn_help",
    "en": "Help",
    "ru": ""
  },
  {
    "id": "epsg_set_projection_export",
    "en": "Set the export projection, using a code from the EPSG format",
    "ru": ""
  },
  {
    "id": "epsg_set_projection_import",
    "en": "Assign a projection system to the data ( code EPSG, optional )",
    "ru": ""
  },
  {
    "id": "epsg_btn_search",
    "en": "Search",
    "ru": ""
  },
  {
    "id": "epsg_placeholder_search",
    "en": "Country or projection name ...",
    "ru": ""
  },
  {
    "id": "epsg_label_search",
    "en": "Enter a country or projection name",
    "ru": ""
  },
  {
    "id": "epsg_placeholder_input",
    "en": "EPSG code. e.g. '4326'",
    "ru": ""
  },
  {
    "id": "epsg_btn_open_search",
    "en": "Find epsg code ...",
    "ru": ""
  },
  {
    "id": "btn_add_source",
    "en": "Add a source layer",
    "ru": ""
  },
  {
    "id": "btn_about",
    "en": "About",
    "ru": ""
  },
  {
    "id": "title_about",
    "en": "About",
    "ru": ""
  },
  {
    "id": "btn_load_new_project",
    "en": "Load the new project",
    "ru": ""
  },
  {
    "id": "btn_add_view",
    "en": "Create a new view",
    "ru": ""
  },
  {
    "id": "btn_show_db_info",
    "en": "Full access",
    "ru": ""
  },
  {
    "id": "btn_show_project_external_views",
    "en": "Manage external views",
    "ru": ""
  },
  {
    "id": "btn_show_db_query_maker",
    "en": "API SQL query maker",
    "ru": ""
  },
  {
    "id": "label_query_write",
    "en": "Write your SQL query",
    "ru": ""
  },
  {
    "id": "label_layer_available",
    "en": "Relations available",
    "ru": ""
  },
  {
    "id": "btn_show_add_project",
    "en": "Add a new project",
    "ru": ""
  },
  {
    "id": "btn_show_add_project_disabled",
    "en": "Add a new project ( disabled )",
    "ru": ""
  },
  {
    "id": "btn_show_db_info_self",
    "en": "Get temporary access to edit a dataset",
    "ru": ""
  },
  {
    "id": "btn_cancel",
    "en": "Cancel",
    "ru": ""
  },
  {
    "id": "btn_copy",
    "en": "Copy",
    "ru": ""
  },
  {
    "id": "btn_geolocate_user",
    "en": "Geolocate",
    "ru": ""
  },
  {
    "id": "btn_close",
    "en": "Close",
    "ru": ""
  },
  {
    "id": "btn_join_project_long",
    "en": "Membership request for this project",
    "ru": ""
  },
  {
    "id": "btn_join_project",
    "en": "Join",
    "ru": ""
  },
  {
    "id": "btn_join_current_project",
    "en": "Join current project ( %s )",
    "ru": ""
  },
  {
    "id": "btn_confirm",
    "en": "Confirm",
    "ru": ""
  },
  {
    "id": "btn_country",
    "en": "Select country",
    "ru": ""
  },
  {
    "id": "btn_create",
    "en": "Create",
    "ru": ""
  },
  {
    "id": "btn_delete",
    "en": "Delete",
    "ru": ""
  },
  {
    "id": "btn_edit_selected",
    "en": "Edit selected",
    "ru": ""
  },
  {
    "id": "btn_edit_source",
    "en": "Manage sources",
    "ru": ""
  },
  {
    "id": "btn_source_overlap_utilities",
    "en": "Area intersection tools",
    "ru": ""
  },
  {
    "id": "btn_source_validate_geom",
    "en": "Geometry validation",
    "ru": ""
  },
  {
    "id": "btn_analyse",
    "en": "Run analysis",
    "ru": ""
  },
  {
    "id": "logs",
    "en": "Logs",
    "ru": ""
  },
  {
    "id": "calc_area_result",
    "en": "Area of intersection (km2)",
    "ru": ""
  },
  {
    "id": "radio_source_overlap_mode",
    "en": "Select analysis",
    "ru": ""
  },
  {
    "id": "source_overlap_mode_area",
    "en": "Calculate area of intersection",
    "ru": ""
  },
  {
    "id": "source_overlap_mode_create_source",
    "en": "Create new layer based on the intersection",
    "ru": ""
  },
  {
    "id": "check_add_source_from_view",
    "en": "Add sources by views",
    "ru": ""
  },
  {
    "id": "select_overlap_source_from_view",
    "en": "Select views",
    "ru": ""
  },
  {
    "id": "btn_add_source_from_view",
    "en": "Add sources from those views",
    "ru": ""
  },
  {
    "id": "select_overlap_layers",
    "en": "Layers : minimum 1, maximum 3, reorder if needed ",
    "ru": ""
  },
  {
    "id": "select_overlap_countries",
    "en": "Country",
    "ru": ""
  },
  {
    "id": "n_layers_more_3",
    "en": "More than three layers selected",
    "ru": ""
  },
  {
    "id": "n_layers_less_1",
    "en": "Less that one layer selected",
    "ru": ""
  },
  {
    "id": "n_country_not_1",
    "en": "Only one country should be selected",
    "ru": ""
  },
  {
    "id": "title_overlap_tools",
    "en": "Area intersection utilities",
    "ru": ""
  },
  {
    "id": "source_overlap_new_source_email_info",
    "en": "An email will be send to '%s' at the end of the process",
    "ru": ""
  },
  {
    "id": "btn_edit_source_metadata",
    "en": "Edit sources metadata",
    "ru": ""
  },
  {
    "id": "btn_finish",
    "en": "Finish",
    "ru": ""
  },
  {
    "id": "btn_fullscreen",
    "en": "Display the app in fullscreen mode",
    "ru": ""
  },
  {
    "id": "btn_get_area_visible",
    "en": "Area of visible features",
    "ru": ""
  },
  {
    "id": "btn_get_overlap_visible",
    "en": "Overlaps to geojson",
    "ru": ""
  },
  {
    "id": "btn_get_layer_summary",
    "en": "Get layer summary",
    "ru": ""
  },
  {
    "id": "btn_iframe_builder",
    "en": "Embed MapX",
    "ru": ""
  },
  {
    "id": "btn_language",
    "en": "Language",
    "ru": ""
  },
  {
    "id": "btn_login",
    "en": "Login window",
    "ru": ""
  },
  {
    "id": "btn_north_arrow",
    "en": "Reset bearing",
    "ru": ""
  },
  {
    "id": "btn_draw_mode",
    "en": "Vector draw tools",
    "ru": ""
  },
  {
    "id": "btn_map_composer",
    "en": "Map composer",
    "ru": ""
  },
  {
    "id": "btn_opt_date",
    "en": "Filter date",
    "ru": ""
  },
  {
    "id": "btn_opt_attribute_table",
    "en": "Attribute table",
    "ru": ""
  },
  {
    "id": "btn_opt_delete",
    "en": "Remove this view",
    "ru": ""
  },
  {
    "id": "btn_opt_home_project",
    "en": "Open original project",
    "ru": ""
  },
  {
    "id": "btn_opt_move_top",
    "en": "Move to top",
    "ru": ""
  },
  {
    "id": "btn_opt_move_bottom",
    "en": "Move to bottom",
    "ru": ""
  },
  {
    "id": "btn_opt_delete_geojson",
    "en": "Delete",
    "ru": ""
  },
  {
    "id": "btn_opt_download",
    "en": "Download the data",
    "ru": ""
  },
  {
    "id": "btn_opt_edit_config",
    "en": "Configure this view",
    "ru": ""
  },
  {
    "id": "btn_opt_edit_custom_code",
    "en": "Edit code",
    "ru": ""
  },
  {
    "id": "btn_opt_edit_dashboard",
    "en": "Edit dashboard",
    "ru": ""
  },
  {
    "id": "btn_opt_edit_story",
    "en": "Edit story map",
    "ru": ""
  },
  {
    "id": "btn_opt_edit_style",
    "en": "Set the style of this view",
    "ru": ""
  },
  {
    "id": "schema_style_title_legend",
    "en": "Legend title",
    "ru": ""
  },
  {
    "id": "schema_style_reverse_order",
    "en": "Reverse displayed layers order",
    "ru": ""
  },
  {
    "id": "schema_style_reverse_order_desc",
    "en": "If checked, the layer stack will be reversed : the top rule will draw a layer at the bottom of the stack",
    "ru": ""
  },
  {
    "id": "schema_style_show_symbol_label",
    "en": "Show symbol with label",
    "ru": ""
  },
  {
    "id": "schema_style_show_symbol_label_desc",
    "en": "If using symbols with point data, should MapX add labels around it?",
    "ru": ""
  },
  {
    "id": "schema_style_hide_nulls",
    "en": "Ignore missing values",
    "ru": ""
  },
  {
    "id": "schema_style_hide_nulls_desc",
    "en": "If checked, null or missing values will be ignored in the style",
    "ru": ""
  },
  {
    "id": "btn_opt_meta",
    "en": "Display metadata",
    "ru": ""
  },
  {
    "id": "btn_opt_numeric",
    "en": "Filter by numeric value",
    "ru": ""
  },
  {
    "id": "btn_opt_reset",
    "en": "Reset the view",
    "ru": ""
  },
  {
    "id": "btn_opt_screenshot",
    "en": "Take a screenshoot",
    "ru": ""
  },
  {
    "id": "btn_opt_search",
    "en": "Settings",
    "ru": ""
  },
  {
    "id": "btn_opt_share",
    "en": "Share a link to this view",
    "ru": ""
  },
  {
    "id": "btn_opt_share_to_project",
    "en": "Share this view in another project",
    "ru": ""
  },
  {
    "id": "share_in_project_no_publisher_project",
    "en": "You have no project yet where to publish this view",
    "ru": ""
  },
  {
    "id": "share_in_project_no_view",
    "en": "No view to share",
    "ru": ""
  },
  {
    "id": "btn_opt_start_story",
    "en": "Read this story map",
    "ru": ""
  },
  {
    "id": "btn_opt_transparency",
    "en": "Transparency",
    "ru": ""
  },
  {
    "id": "btn_opt_zoom_all",
    "en": "Zoom to all features",
    "ru": ""
  },
  {
    "id": "btn_opt_zoom_visible",
    "en": "Zoom on displayed features",
    "ru": ""
  },
  {
    "id": "btn_preview",
    "en": "Preview",
    "ru": ""
  },
  {
    "id": "btn_selfdb_generate_info",
    "en": "Generate",
    "ru": ""
  },
  {
    "id": "btn_print",
    "en": "Print current",
    "ru": ""
  },
  {
    "id": "btn_reset",
    "en": "Reset",
    "ru": ""
  },
  {
    "id": "btn_save",
    "en": "Save",
    "ru": ""
  },
  {
    "id": "btn_send",
    "en": "Submit",
    "ru": ""
  },
  {
    "id": "btn_show_app_config",
    "en": "Configuration",
    "ru": ""
  },
  {
    "id": "btn_show_project_config",
    "en": "Project configuration",
    "ru": ""
  },
  {
    "id": "btn_show_project_views_states",
    "en": "Save views list state",
    "ru": ""
  },
  {
    "id": "btn_show_project_delete",
    "en": "Delete this project",
    "ru": ""
  },
  {
    "id": "btn_show_project_delete_disabled",
    "en": "Delete this project ( disabled )",
    "ru": ""
  },
  {
    "id": "btn_show_role_manager",
    "en": "Define roles",
    "ru": ""
  },
  {
    "id": "btn_sort_date",
    "en": "Date",
    "ru": ""
  },
  {
    "id": "btn_filter_checked",
    "en": "Filter activated views",
    "ru": ""
  },
  {
    "id": "btn_filter_show_panel",
    "en": "Advanced filter",
    "ru": ""
  },
  {
    "id": "btn_sort_title",
    "en": "Title",
    "ru": ""
  },
  {
    "id": "sort_label",
    "en": "Sort by",
    "ru": ""
  },
  {
    "id": "btn_story_unlock_map",
    "en": "Toggle map interaction",
    "ru": ""
  },
  {
    "id": "btn_story_close",
    "en": "Back to the map explorer",
    "ru": ""
  },
  {
    "id": "btn_story_edit_cancel",
    "en": "Cancel edition",
    "ru": ""
  },
  {
    "id": "btn_story_edit_save",
    "en": "Save edition",
    "ru": ""
  },
  {
    "id": "btn_story_edit",
    "en": "Start edition",
    "ru": ""
  },
  {
    "id": "btn_switchui",
    "en": "Toggle the color of the interface",
    "ru": ""
  },
  {
    "id": "btn_tab_dashboard",
    "en": "Toggle dashboards",
    "ru": ""
  },
  {
    "id": "btn_tab_settings",
    "en": "Settings ",
    "ru": ""
  },
  {
    "id": "btn_tab_tools",
    "en": "Toolbox",
    "ru": ""
  },
  {
    "id": "btn_tab_views",
    "en": "Views",
    "ru": ""
  },
  {
    "id": "btn_theme_switch",
    "en": "Switch theme",
    "ru": ""
  },
  {
    "id": "btn_theme_sat",
    "en": "Switch theme : aerial",
    "ru": ""
  },
  {
    "id": "btn_toggle_all",
    "en": "Immersive mode",
    "ru": ""
  },
  {
    "id": "btn_update",
    "en": "Update  ",
    "ru": ""
  },
  {
    "id": "btn_upload",
    "en": "Upload",
    "ru": ""
  },
  {
    "id": "btn_zoom_in",
    "en": "Zoom in",
    "ru": ""
  },
  {
    "id": "btn_zoom_out",
    "en": "Zoom out",
    "ru": ""
  },
  {
    "id": "btn_overlap_spotlight",
    "en": "Highlight vector features",
    "ru": ""
  },
  {
    "id": "title_config_highlight",
    "en": "Highlight tool configuration",
    "ru": ""
  },
  {
    "id": "select_highlight_mode",
    "en": "Select highlight mode",
    "ru": ""
  },
  {
    "id": "label_check_instant_overlap",
    "en": "Enable overlap area estimation",
    "ru": ""
  },
  {
    "id": "label_area_instant_overlap",
    "en": "Instant area estimation",
    "ru": ""
  },
  {
    "id": "label_help_area_instant_overlap",
    "en": "The overlap surface is estimated using a spherical representation of the Earth. The result will vary depending on the data quality, current filters and current resolution.",
    "ru": ""
  },
  {
    "id": "label_resol_instant_overlap",
    "en": "Current resolution",
    "ru": ""
  },
  {
    "id": "label_help_resol_instant_overlap",
    "en": "The current resolution depends on the zoom level and latitude. It represents the average area covered by one pixel.",
    "ru": ""
  },
  {
    "id": "categorical",
    "en": "Categorical",
    "ru": ""
  },
  {
    "id": "cc",
    "en": "Custom code",
    "ru": ""
  },
  {
    "id": "center",
    "en": "Center",
    "ru": ""
  },
  {
    "id": "country",
    "en": "Country",
    "ru": ""
  },
  {
    "id": "create",
    "en": "Create",
    "ru": ""
  },
  {
    "id": "content",
    "en": "Content",
    "ru": ""
  },
  {
    "id": "title",
    "en": "Title",
    "ru": ""
  },
  {
    "id": "join_project",
    "en": "Join",
    "ru": ""
  },
  {
    "id": "dev",
    "en": "Development",
    "ru": ""
  },
  {
    "id": "env",
    "en": "Environment",
    "ru": ""
  },
  {
    "id": "error_no_layer",
    "en": "No source layer set",
    "ru": ""
  },
  {
    "id": "error_form_issues",
    "en": "There are some issues in the form, please correct them",
    "ru": ""
  },
  {
    "id": "warning_delete_project",
    "en": "Project deletion also remove all views, data, settings and anything related to this project, including views used in other project. Data shared from other project will be preserved",
    "ru": ""
  },
  {
    "id": "error_no_source",
    "en": "No source layer found",
    "ru": ""
  },
  {
    "id": "error_title_exists",
    "en": "This title already exists",
    "ru": ""
  },
  {
    "id": "error_title_no_match",
    "en": "The title does not match",
    "ru": ""
  },
  {
    "id": "error_title_short",
    "en": "The title is too short",
    "ru": ""
  },
  {
    "id": "error_title_not_valid",
    "en": "The title is not valid",
    "ru": ""
  },
  {
    "id": "error_description_short",
    "en": "The description is too short",
    "ru": ""
  },
  {
    "id": "error_title_bad",
    "en": "The title is not valid",
    "ru": ""
  },
  {
    "id": "error_project_default_not_public",
    "en": "The default project must be public",
    "ru": ""
  },
  {
    "id": "error_email_not_valid",
    "en": "This email is not valid",
    "ru": ""
  },
  {
    "id": "error_email_is_member",
    "en": "This email is already registered in this project",
    "ru": ""
  },
  {
    "id": "error_email_bad",
    "en": "This email is not accepted",
    "ru": ""
  },
  {
    "id": "error_email_confirm_too_old",
    "en": "This confirmation email is too old",
    "ru": ""
  },
  {
    "id": "error_msg_too_long",
    "en": "This message is too long",
    "ru": ""
  },
  {
    "id": "error_msg_too_short",
    "en": "This message is too short",
    "ru": ""
  },
  {
    "id": "error_email_not_registered",
    "en": "This email does not belongs to a current MapX user. Once open, the activation link will also create automatically a new account on MapX.",
    "ru": ""
  },
  {
    "id": "error_email_already_member",
    "en": "A user with this email is already registered",
    "ru": ""
  },
  {
    "id": "error_description_bad",
    "en": "The description is not valid",
    "ru": ""
  },
  {
    "id": "error_title_long",
    "en": "The title is to long",
    "ru": ""
  },
  {
    "id": "error_description_long",
    "en": "The description is to long",
    "ru": ""
  },
  {
    "id": "error_cant_geolocate_msg",
    "en": "Sorry, MapX can't find your position",
    "ru": ""
  },
  {
    "id": "error_geolocate_issue",
    "en": "Geolocation issue",
    "ru": ""
  },
  {
    "id": "exponential",
    "en": "Continuous",
    "ru": ""
  },
  {
    "id": "ext",
    "en": "Extractive",
    "ru": ""
  },
  {
    "id": "fold_view_legend",
    "en": "Legend",
    "ru": ""
  },
  {
    "id": "fold_view_tools",
    "en": "Tools",
    "ru": ""
  },
  {
    "id": "fold_views_filter",
    "en": "Filter options",
    "ru": ""
  },
  {
    "id": "fold_views_sort",
    "en": "Sort views",
    "ru": ""
  },
  {
    "id": "gj",
    "en": "Local GeoJSON",
    "ru": ""
  },
  {
    "id": "inf",
    "en": "Infrastructure",
    "ru": ""
  },
  {
    "id": "interval",
    "en": "Interval",
    "ru": ""
  },
  {
    "id": "time_slider",
    "en": "Time slider",
    "ru": ""
  },
  {
    "id": "custom_code",
    "en": "Custom code",
    "ru": ""
  },
  {
    "id": "custom_style",
    "en": "Custom style",
    "ru": ""
  },
  {
    "id": "custom_style_edit",
    "en": "Edit custom style",
    "ru": ""
  },
  {
    "id": "story_map",
    "en": "Story map",
    "ru": ""
  },
  {
    "id": "dashboard",
    "en": "Dashboard",
    "ru": ""
  },
  {
    "id": "overlap",
    "en": "Overlap",
    "ru": ""
  },
  {
    "id": "left",
    "en": "Left",
    "ru": ""
  },
  {
    "id": "line",
    "en": "Line",
    "ru": ""
  },
  {
    "id": "loading_img",
    "en": "Image loading, please wait ...",
    "ru": ""
  },
  {
    "id": "login_cancel",
    "en": "Cancel",
    "ru": ""
  },
  {
    "id": "login_pwd_mail_sent",
    "en": "An email has been sent, please check your inbox and copy the received password in the field below",
    "ru": ""
  },
  {
    "id": "login_pwd_mail_sent_error",
    "en": "An error occuried, we were not able to send you the single usage password. Please try again later.",
    "ru": ""
  },
  {
    "id": "login_project",
    "en": "Project or country name in which the role applies",
    "ru": ""
  },
  {
    "id": "login_email",
    "en": "Email",
    "ru": ""
  },
  {
    "id": "login_insert_pwd",
    "en": "Insert the single usage password",
    "ru": ""
  },
  {
    "id": "login_info_box",
    "en": "If you are not yet registered, a successful authentication will create a new account, and unlock new features. If you are already registered, a successful authentication will additionally give you access to all projects where you are already a member. User registration with MapX implies consent to collect and publish performance data of non-personally identifiable information at an aggregate level.",
    "ru": ""
  },
  {
    "id": "login_out",
    "en": "Log out",
    "ru": ""
  },
  {
    "id": "login_groups",
    "en": "Groups",
    "ru": ""
  },
  {
    "id": "login_send_pwd",
    "en": "Send",
    "ru": ""
  },
  {
    "id": "login_subtitle",
    "en": "Please enter your email to receive a single usage secure password",
    "ru": ""
  },
  {
    "id": "login_title",
    "en": "Log in",
    "ru": ""
  },
  {
    "id": "login_user_status",
    "en": "User status",
    "ru": ""
  },
  {
    "id": "more",
    "en": "More",
    "ru": ""
  },
  {
    "id": "noAbstract",
    "en": "[ Abstract missing ]",
    "ru": ""
  },
  {
    "id": "noLegend",
    "en": "[ Missing legend ]",
    "ru": ""
  },
  {
    "id": "noData",
    "en": "[ Missing value ]",
    "ru": ""
  },
  {
    "id": "noFilter",
    "en": "[ No filter ]",
    "ru": ""
  },
  {
    "id": "noLayer",
    "en": "[ No source layer ]",
    "ru": ""
  },
  {
    "id": "noValue",
    "en": "[ No value ]",
    "ru": ""
  },
  {
    "id": "property_list_failed",
    "en": "[ Failed to display attributes ]",
    "ru": ""
  },
  {
    "id": "none",
    "en": "None",
    "ru": ""
  },
  {
    "id": "noSelect",
    "en": "[ Empty selection ]",
    "ru": ""
  },
  {
    "id": "noTitle",
    "en": "[ Title missing ]",
    "ru": ""
  },
  {
    "id": "noVariable",
    "en": "[ Missing value ]",
    "ru": ""
  },
  {
    "id": "noViewOrig",
    "en": "[ No view available ]",
    "ru": ""
  },
  {
    "id": "noView",
    "en": "[ Select a different project, category or country to display available data ]",
    "ru": ""
  },
  {
    "id": "view_fetching_progress",
    "en": "[ {{vOk}}/{{vTot}} ]",
    "ru": ""
  },
  {
    "id": "nrg",
    "en": "Energy",
    "ru": ""
  },
  {
    "id": "old_add_view",
    "en": "Add a new view",
    "ru": ""
  },
  {
    "id": "oth",
    "en": "Other",
    "ru": ""
  },
  {
    "id": "point",
    "en": "Point",
    "ru": ""
  },
  {
    "id": "pol",
    "en": "Politics",
    "ru": ""
  },
  {
    "id": "polygon",
    "en": "Polygon",
    "ru": ""
  },
  {
    "id": "public",
    "en": "Public",
    "ru": ""
  },
  {
    "id": "publish",
    "en": "Publish",
    "ru": ""
  },
  {
    "id": "publisher",
    "en": "Publisher",
    "ru": ""
  },
  {
    "id": "publishers",
    "en": "Publishers",
    "ru": ""
  },
  {
    "id": "member",
    "en": "Member",
    "ru": ""
  },
  {
    "id": "members",
    "en": "Members",
    "ru": ""
  },
  {
    "id": "right",
    "en": "Right",
    "ru": ""
  },
  {
    "id": "rt",
    "en": "Raster tiles",
    "ru": ""
  },
  {
    "id": "sat",
    "en": "Satellite imagery",
    "ru": ""
  },
  {
    "id": "save",
    "en": "Save",
    "ru": ""
  },
  {
    "id": "saved_at",
    "en": "Saved at %s",
    "ru": ""
  },
  {
    "id": "email",
    "en": "Email",
    "ru": ""
  },
  {
    "id": "from",
    "en": "From",
    "ru": ""
  },
  {
    "id": "to",
    "en": "To",
    "ru": ""
  },
  {
    "id": "invite_member_email",
    "en": "Invite a new member",
    "ru": ""
  },
  {
    "id": "btn_invite",
    "en": "Invite",
    "ru": ""
  },
  {
    "id": "schema_class",
    "en": "Class",
    "ru": ""
  },
  {
    "id": "schema_style_nulls",
    "en": "Missing values",
    "ru": ""
  },
  {
    "id": "schema_style_color",
    "en": "Color",
    "ru": ""
  },
  {
    "id": "schema_style_description",
    "en": "Description",
    "ru": ""
  },
  {
    "id": "schema_item",
    "en": "Item",
    "ru": ""
  },
  {
    "id": "schema_key",
    "en": "Key",
    "ru": ""
  },
  {
    "id": "schema_style_label",
    "en": "Label",
    "ru": ""
  },
  {
    "id": "schema_style_last_rule",
    "en": "Last rule",
    "ru": ""
  },
  {
    "id": "schema_metadata",
    "en": "Meta data",
    "ru": ""
  },
  {
    "id": "schema_method",
    "en": "Method",
    "ru": ""
  },
  {
    "id": "schema_style_opacity",
    "en": "Opacity",
    "ru": ""
  },
  {
    "id": "schema_style_rule",
    "en": "Rule",
    "ru": ""
  },
  {
    "id": "schema_style_rules",
    "en": "Rules",
    "ru": ""
  },
  {
    "id": "schema_style_size",
    "en": "Size",
    "ru": ""
  },
  {
    "id": "schema_style_config_zoom",
    "en": "Zoom settings",
    "ru": ""
  },
  {
    "id": "schema_style_size_zoom_max",
    "en": "Coeficient of size at zoom max",
    "ru": ""
  },
  {
    "id": "schema_style_size_zoom_min",
    "en": "Coeficient of size at zoom min",
    "ru": ""
  },
  {
    "id": "schema_style_size_zoom_exponent",
    "en": "Size interpolation exponent",
    "ru": ""
  },
  {
    "id": "schema_style_size_zoom_exponent_desc",
    "en": "Size interpolation exponent function. A value of 1 give a linear interpolation.",
    "ru": ""
  },
  {
    "id": "schema_style_zoom_max",
    "en": "Zoom max",
    "ru": ""
  },
  {
    "id": "schema_style_zoom_min",
    "en": "Zoom min",
    "ru": ""
  },
  {
    "id": "schema_style_sprite",
    "en": "Symbol",
    "ru": "Símbolo"
  },
  {
    "id": "schema_style_size_zoom_min_desc",
    "en": "If greater than 0, coefficient of the size for lines and points at zoom min.",
    "ru": ""
  },
  {
    "id": "schema_style_size_zoom_max_desc",
    "en": "If greater than 0, coefficient of the size for lines and points at zoom max.",
    "ru": ""
  },
  {
    "id": "schema_style_zoom_min_desc",
    "en": "Minimum zoom to show the data",
    "ru": ""
  },
  {
    "id": "schema_style_zoom_max_desc",
    "en": "Maximum zoom to display the data",
    "ru": ""
  },
  {
    "id": "schema_style_sprite",
    "en": "Symbol",
    "ru": ""
  },
  {
    "id": "schema_story_tips_title",
    "en": "Tips:",
    "ru": ""
  },
  {
    "id": "schema_story_tips",
    "en": "<p>Here is a list of good practices to provide a seamless experience for readers:</p><ol><li>Keep it simple.</li><li>It is better to create short story maps to keep the interest of your audience.</li><li>For good readability, it is recommended not to exceed two slides per steps and more than two layers on the map in the same step.</li><li>Pictures, videos and infographics can be useful and impactful mediums to contextualize your story. However, they should not overshadow the spatial component of your story. Maps should be at its center.</li><li>Effects, transitions or 3d transformations can affect the readability of your story map on slow devices, use them sparingly.</li></ol>",
    "ru": ""
  },
  {
    "id": "schema_story_author",
    "en": "Author of the story",
    "ru": "Autor del mapa narrativo"
  },
  {
    "id": "schema_story_map_pos",
    "en": "Position of the map",
    "ru": ""
  },
  {
    "id": "schema_story_meta",
    "en": "Metadata",
    "ru": ""
  },
  {
    "id": "schema_story_org",
    "en": "Organisation name",
    "ru": ""
  },
  {
    "id": "schema_story_pos_get",
    "en": "Update using current map parameters",
    "ru": ""
  },
  {
    "id": "schema_story_slide",
    "en": "Slide",
    "ru": ""
  },
  {
    "id": "schema_story_slide_color",
    "en": "Color theme",
    "ru": ""
  },
  {
    "id": "schema_story_slide_color_bg",
    "en": "Background color",
    "ru": ""
  },
  {
    "id": "schema_story_slide_color_fg",
    "en": "Text color",
    "ru": ""
  },
  {
    "id": "schema_story_slide_config",
    "en": "Configuration",
    "ru": ""
  },
  {
    "id": "schema_story_slide_layout",
    "en": "Content layout",
    "ru": ""
  },
  {
    "id": "schema_story_slide_opacity_bg",
    "en": "Background opacity",
    "ru": ""
  },
  {
    "id": "schema_story_slide_pos_z",
    "en": "Depth (z axis)",
    "ru": ""
  },
  {
    "id": "schema_story_slide_speed",
    "en": "Speed ratio",
    "ru": ""
  },
  {
    "id": "schema_story_slides",
    "en": "Slides",
    "ru": ""
  },
  {
    "id": "schema_story_step",
    "en": "Step",
    "ru": ""
  },
  {
    "id": "schema_story_step_content",
    "en": "Content",
    "ru": ""
  },
  {
    "id": "schema_story_step_title",
    "en": "Title ",
    "ru": ""
  },
  {
    "id": "schema_story_steps",
    "en": "Steps",
    "ru": ""
  },
  {
    "id": "schema_story_steps_title",
    "en": "Steps of the story",
    "ru": ""
  },
  {
    "id": "schema_story_text_pos",
    "en": "Text position",
    "ru": ""
  },
  {
    "id": "schema_story_title",
    "en": "Story",
    "ru": ""
  },
  {
    "id": "schema_style_value",
    "en": "Value",
    "ru": ""
  },
  {
    "id": "self",
    "en": "Myself",
    "ru": ""
  },
  {
    "id": "sm",
    "en": "Story map",
    "ru": ""
  },
  {
    "id": "soc",
    "en": "Social",
    "ru": ""
  },
  {
    "id": "source_meta_data",
    "en": "Metadata for the source",
    "ru": ""
  },
  {
    "id": "source_confirm_remove",
    "en": "Confirm source deletion",
    "ru": ""
  },
  {
    "id": "source_allow_download",
    "en": "Allow download",
    "ru": ""
  },
  {
    "id": "source_allow_WMS",
    "en": "Activate WMS",
    "ru": ""
  },
  {
    "id": "source_allow_WFS",
    "en": "Activate WFS",
    "ru": ""
  },
  {
    "id": "source_removed",
    "en": "Source deleted",
    "ru": ""
  },
  {
    "id": "source_raster_tile_legend",
    "en": "URL of the legend (png)",
    "ru": ""
  },
  {
    "id": "source_raster_tile_size",
    "en": "Size of the tiles (pixels)",
    "ru": ""
  },
  {
    "id": "source_raster_tile_url",
    "en": "URL of tiles endpoint ",
    "ru": ""
  },
  {
    "id": "source_raster_tile_url_download",
    "en": "Download link",
    "ru": ""
  },
  {
    "id": "source_raster_tile_url_metadata",
    "en": "Link to the metadata",
    "ru": ""
  },
  {
    "id": "source_select_geometry",
    "en": "Source geometry type",
    "ru": ""
  },
  {
    "id": "source_select_layer",
    "en": "Source layer",
    "ru": ""
  },
  {
    "id": "source_select_layer_mask",
    "en": "Source layer mask",
    "ru": ""
  },
  {
    "id": "source_select_variable",
    "en": "Source attribute",
    "ru": ""
  },
  {
    "id": "source_select_variable_alt",
    "en": "Secondary attributes",
    "ru": ""
  },
  {
    "id": "source_select_variable_alt",
    "en": "Secondary attributes",
    "ru": ""
  },
  {
    "id": "source_target_readers",
    "en": "Groups with use access ",
    "ru": ""
  },
  {
    "id": "source_target_editors",
    "en": "Groups with write access",
    "ru": ""
  },
  {
    "id": "source_services",
    "en": "Services",
    "ru": ""
  },
  {
    "id": "source_validate_title",
    "en": "Geometry validation tool",
    "ru": ""
  },
  {
    "id": "source_validate_geom_show_expert_options",
    "en": "Show expert options",
    "ru": ""
  },
  {
    "id": "source_validate_geom_use_cache",
    "en": "Use cached results – if any – instead of recalculate",
    "ru": ""
  },
  {
    "id": "source_validate_geom_auto_correct",
    "en": "Try an automatic correction ( experimental )",
    "ru": ""
  },
  {
    "id": "source_validate_geom_auto_correct_info",
    "en": "Warning, this could alter the geometry. For (multi) polygons, the automatic correction use a buffer of 0 around each feature. For other types, ST_MakeValid is used.",
    "ru": ""
  },
  {
    "id": "download_select_format_vector",
    "en": "Output format",
    "ru": ""
  },
  {
    "id": "download_select_by_countries",
    "en": "Country used to spatially extract the data (clip)",
    "ru": ""
  },
  {
    "id": "download_file_name",
    "en": "Filename",
    "ru": ""
  },
  {
    "id": "source_sum_geom_type",
    "en": "Type of the geometry",
    "ru": ""
  },
  {
    "id": "source_sum_n_distinct",
    "en": "Number of distinct values",
    "ru": ""
  },
  {
    "id": "source_sum_n_null",
    "en": "Number of missing or null values",
    "ru": ""
  },
  {
    "id": "source_sum_n_row",
    "en": "Number of values",
    "ru": ""
  },
  {
    "id": "source_sum_sample",
    "en": "Sample values",
    "ru": ""
  },
  {
    "id": "source_sum_title",
    "en": "Variable summary",
    "ru": ""
  },
  {
    "id": "source_sum_variable_type",
    "en": "Type of the attribut",
    "ru": ""
  },
  {
    "id": "source_summary_check",
    "en": "Show attribut summary",
    "ru": ""
  },
  {
    "id": "source_time_range",
    "en": "Time range",
    "ru": ""
  },
  {
    "id": "source_title",
    "en": "Source title",
    "ru": ""
  },
  {
    "id": "str",
    "en": "Stress",
    "ru": ""
  },
  {
    "id": "superuser",
    "en": "Superuser",
    "ru": ""
  },
  {
    "id": "title_app",
    "en": "MapX",
    "ru": "MapX"
  },
  {
    "id": "user_profile",
    "en": "User profile",
    "ru": ""
  },
  {
    "id": "user_authentication",
    "en": "Authentication",
    "ru": ""
  },
  {
    "id": "title_settings",
    "en": "Settings",
    "ru": ""
  },
  {
    "id": "title_settings_colors",
    "en": "Theme configuration",
    "ru": ""
  },
  {
    "id": "title_tools",
    "en": "Tools",
    "ru": ""
  },
  {
    "id": "title_tools_db",
    "en": "Database",
    "ru": ""
  },
  {
    "id": "title_tools_admin_project",
    "en": "Projects",
    "ru": ""
  },
  {
    "id": "title_tools_config",
    "en": "Configuration",
    "ru": ""
  },
  {
    "id": "title_tools_map",
    "en": "Map",
    "ru": ""
  },
  {
    "id": "title_tools_share",
    "en": "Share",
    "ru": ""
  },
  {
    "id": "title_tools_sources",
    "en": "Sources",
    "ru": ""
  },
  {
    "id": "title_tools_views",
    "en": "Views",
    "ru": ""
  },
  {
    "id": "title_tools_dbself_info",
    "en": "Connection information",
    "ru": ""
  },
  {
    "id": "title_tools_dbself_select",
    "en": "Select source(s) to edit",
    "ru": ""
  },
  {
    "id": "title_views",
    "en": "Views",
    "ru": ""
  },
  {
    "id": "top",
    "en": "Top",
    "ru": ""
  },
  {
    "id": "ui_country",
    "en": "Select country",
    "ru": ""
  },
  {
    "id": "ui_project",
    "en": "Select project",
    "ru": ""
  },
  {
    "id": "select_member_project",
    "en": "Switch to another project where you are a member",
    "ru": ""
  },
  {
    "id": "ui_language",
    "en": "Language of the interface",
    "ru": "Язык интерфейса."
  },
  {
    "id": "update_view_list",
    "en": "Update view list",
    "ru": ""
  },
  {
    "id": "user",
    "en": "Registered user",
    "ru": ""
  },
  {
    "id": "group_project",
    "en": "Groups in project",
    "ru": ""
  },
  {
    "id": "view",
    "en": "View",
    "ru": ""
  },
  {
    "id": "views",
    "en": "Views",
    "ru": ""
  },
  {
    "id": "views_external",
    "en": "External views",
    "ru": ""
  },
  {
    "id": "views_external_modal_title",
    "en": "Manage external views",
    "ru": ""
  },
  {
    "id": "view_project_short",
    "en": "( p )",
    "ru": ""
  },
  {
    "id": "view_external_short",
    "en": "( e )",
    "ru": ""
  },
  {
    "id": "view_shared",
    "en": "View shared",
    "ru": ""
  },
  {
    "id": "view_delete_modal_title",
    "en": "View to delete %s",
    "ru": ""
  },
  {
    "id": "view_edit_custom_code_modal_title",
    "en": "Edit custom code of %s",
    "ru": ""
  },
  {
    "id": "view_edit_dashboard_modal_title",
    "en": "Edit dashboard of  %s",
    "ru": ""
  },
  {
    "id": "view_edit_story_modal_title",
    "en": "Edit story map of  %s",
    "ru": ""
  },
  {
    "id": "view_edit_style_modal_title",
    "en": "Edit style of  %s",
    "ru": ""
  },
  {
    "id": "view_abstract",
    "en": "View abstract",
    "ru": ""
  },
  {
    "id": "view_add_dashboard",
    "en": "Add a dashboard",
    "ru": ""
  },
  {
    "id": "view_add_download_btn",
    "en": "Allow download of the source",
    "ru": ""
  },
  {
    "id": "view_add_overlap_layer",
    "en": "Add an mask",
    "ru": ""
  },
  {
    "id": "view_component",
    "en": "Type of views",
    "ru": ""
  },
  {
    "id": "view_components",
    "en": "Types of views",
    "ru": ""
  },
  {
    "id": "view_collections",
    "en": "Collections",
    "ru": ""
  },
  {
    "id": "view_projects",
    "en": "Other projects where the view is visible",
    "ru": ""
  },
  {
    "id": "view_project",
    "en": "Project of the view",
    "ru": ""
  },
  {
    "id": "view_country",
    "en": "Country of the view",
    "ru": ""
  },
  {
    "id": "view_dashboard",
    "en": "Dashboard",
    "ru": ""
  },
  {
    "id": "view_dashboard_config",
    "en": "Configure a dashboard",
    "ru": ""
  },
  {
    "id": "view_dashboard_script",
    "en": "Your script",
    "ru": ""
  },
  {
    "id": "view_dashboard_src_layerChange",
    "en": "All attributes and values from the displayed features",
    "ru": ""
  },
  {
    "id": "view_dashboard_src_layerClick",
    "en": "All attributes and values from the clicked feature",
    "ru": ""
  },
  {
    "id": "view_dashboard_src_none",
    "en": "None. Value provided by the script.",
    "ru": ""
  },
  {
    "id": "view_dashboard_src_view",
    "en": "The frequency table of the selected attribute",
    "ru": ""
  },
  {
    "id": "view_dashboard_src_mousemove",
    "en": "All attributes and values at mouse position",
    "ru": ""
  },
  {
    "id": "view_dashboard_title",
    "en": "Dashboard title",
    "ru": ""
  },
  {
    "id": "view_dashboard_txt_layout",
    "en": "Initial dashboard layout",
    "ru": ""
  },
  {
    "id": "view_dashboard_txt_desc_layout",
    "en": "Set the initial dashboard layout",
    "ru": ""
  },
  {
    "id": "view_dashboard_txt_layout_horizontal",
    "en": "Horizontal",
    "ru": ""
  },
  {
    "id": "view_dashboard_txt_layout_full",
    "en": "Full size",
    "ru": ""
  },
  {
    "id": "view_dashboard_txt_layout_fit",
    "en": "Fit to largest widget",
    "ru": ""
  },
  {
    "id": "view_dashboard_txt_layout_vertical",
    "en": "Vertical",
    "ru": ""
  },
  {
    "id": "view_dashboard_txt_layout_horizontal",
    "en": "Horizontal",
    "ru": ""
  },
  {
    "id": "view_dashboard_txt_height",
    "en": "Height class",
    "ru": ""
  },
  {
    "id": "view_dashboard_txt_script",
    "en": "Your script",
    "ru": ""
  },
  {
    "id": "view_dashboard_txt_add_background_color",
    "en": "Add background color",
    "ru": ""
  },
  {
    "id": "view_dashboard_txt_color_background",
    "en": "Background color",
    "ru": ""
  },
  {
    "id": "view_dashboard_txt_which_data",
    "en": "Which source to use for the data ?",
    "ru": ""
  },
  {
    "id": "view_dashboard_txt_ignore_empty_data",
    "en": "Ignore events that returns an empty array ?",
    "ru": ""
  },
  {
    "id": "view_dashboard_txt_which_module",
    "en": "Which modules to load?",
    "ru": ""
  },
  {
    "id": "view_dashboard_txt_desc_module",
    "en": "Modules will be loaded under `widget.modules`",
    "ru": ""
  },
  {
    "id": "view_dashboard_txt_width",
    "en": "Width class",
    "ru": ""
  },
  {
    "id": "view_dashboard_widget",
    "en": "Widget",
    "ru": ""
  },
  {
    "id": "view_dashboard_widgets",
    "en": "Widgets",
    "ru": ""
  },
  {
    "id": "view_delete_confirm",
    "en": "Click on the confirm button to delete this view, its history and all translations.",
    "ru": ""
  },
  {
    "id": "view_remove_dashboard_confirm",
    "en": "Click on the confirm to remove permanently the dashboard",
    "ru": ""
  },
  {
    "id": "view_remove_dashboard_confirm_title",
    "en": "Confirmation",
    "ru": ""
  },
  {
    "id": "view_download_layer",
    "en": "Download the source layer",
    "ru": ""
  },
  {
    "id": "view_edit_current",
    "en": "Edit view",
    "ru": ""
  },
  {
    "id": "source_edit_metadata",
    "en": "Edit source metadata",
    "ru": ""
  },
  {
    "id": "source_edit",
    "en": "Edit source",
    "ru": ""
  },
  {
    "id": "view_id",
    "en": "View identifier",
    "ru": ""
  },
  {
    "id": "view_new_created",
    "en": "View created",
    "ru": ""
  },
  {
    "id": "view_new_text",
    "en": "Create a new View",
    "ru": ""
  },
  {
    "id": "view_no_layer_found",
    "en": "No source layer found",
    "ru": ""
  },
  {
    "id": "view_num_overlap",
    "en": "Number of overlaps",
    "ru": ""
  },
  {
    "id": "view_filter_input",
    "en": "Filter views ...",
    "ru": ""
  },
  {
    "id": "view_filter_by_tags",
    "en": "Filter views by tag",
    "ru": ""
  },
  {
    "id": "view_search_values",
    "en": "Search values",
    "ru": ""
  },
  {
    "id": "view_filter_by_values",
    "en": "Filter by values",
    "ru": ""
  },
  {
    "id": "view_show_abstract_languages",
    "en": "Show other languages abstract",
    "ru": ""
  },
  {
    "id": "view_show_title_languages",
    "en": "Show other languages titles",
    "ru": ""
  },
  {
    "id": "view_target",
    "en": "Target group. Who can view this.",
    "ru": ""
  },
  {
    "id": "view_target_readers",
    "en": "Read access groups",
    "ru": ""
  },
  {
    "id": "view_target_editors",
    "en": "Edit access groups",
    "ru": ""
  },
  {
    "id": "view_text",
    "en": "View text",
    "ru": ""
  },
  {
    "id": "view_title",
    "en": "View title",
    "ru": ""
  },
  {
    "id": "view_type_select",
    "en": "Type of the view",
    "ru": ""
  },
  {
    "id": "vt",
    "en": "Vector tiles",
    "ru": ""
  },
  {
    "id": "wms",
    "en": "Web Map Service (wms)",
    "ru": ""
  },
  {
    "id": "mx_download",
    "en": "Allow this source to be downloaded",
    "ru": ""
  },
  {
    "id": "gs_ws_a",
    "en": "Publish all related views via WMS",
    "ru": ""
  },
  {
    "id": "gs_ws_b",
    "en": "Publish all related views via WMS/WFS/WCS",
    "ru": ""
  },
  {
    "id": "src_download_issues",
    "en": "The source can't be downloaded",
    "ru": ""
  },
  {
    "id": "src_upload_add",
    "en": "Upload a new source layer",
    "ru": ""
  },
  {
    "id": "src_upload_issues",
    "en": "Upload issue(s)",
    "ru": ""
  },
  {
    "id": "source_upload_vector",
    "en": "Upload new vector source",
    "ru": ""
  },
  {
    "id": "upload_source_title",
    "en": "Title of the new source",
    "ru": ""
  },
  {
    "id": "you_not_logged_in",
    "en": "You are not logged in.",
    "ru": ""
  },
  {
    "id": "you_not_allowed",
    "en": "You are not allowed to do this.",
    "ru": ""
  },
  {
    "id": "src_download_disabled",
    "en": "The download is not allowed.",
    "ru": ""
  },
  {
    "id": "mx_ui_text",
    "en": "Text of the interface",
    "ru": ""
  },
  {
    "id": "mx_ui_link",
    "en": "Links",
    "ru": ""
  },
  {
    "id": "mx_ui_text_faded",
    "en": "Secondary text color",
    "ru": ""
  },
  {
    "id": "mx_ui_hidden",
    "en": "Hidden elements",
    "ru": ""
  },
  {
    "id": "mx_ui_border",
    "en": "Borders",
    "ru": ""
  },
  {
    "id": "mx_ui_background",
    "en": "Background",
    "ru": ""
  },
  {
    "id": "mx_ui_shadow",
    "en": "Shadows",
    "ru": ""
  },
  {
    "id": "mx_map_background",
    "en": "Map: background",
    "ru": ""
  },
  {
    "id": "mx_map_hillshade_shadow",
    "en": "Map: hillshade shadow",
    "ru": ""
  },
  {
    "id": "mx_map_hillshade_highlight",
    "en": "Map: hillshade highlight",
    "ru": ""
  },
  {
    "id": "mx_map_hillshade_accent",
    "en": "Map: hillshade accent",
    "ru": ""
  },
  {
    "id": "mx_map_mask",
    "en": "Map: country shadow",
    "ru": ""
  },
  {
    "id": "mx_map_water",
    "en": "Map: water",
    "ru": ""
  },
  {
    "id": "mx_map_bathymetry_low",
    "en": "Map: bathymetry (low)",
    "ru": ""
  },
  {
    "id": "mx_map_bathymetry_high",
    "en": "Map: bathymetry (high)",
    "ru": ""
  },
  {
    "id": "mx_map_road",
    "en": "Map: road",
    "ru": ""
  },
  {
    "id": "mx_map_road_border",
    "en": "Map: road border",
    "ru": ""
  },
  {
    "id": "mx_map_building",
    "en": "Map: buildings",
    "ru": ""
  },
  {
    "id": "mx_map_boundary_un_1",
    "en": "Map: International boundary",
    "ru": ""
  },
  {
    "id": "mx_map_boundary_un_2",
    "en": "Map: Special boundary line",
    "ru": ""
  },
  {
    "id": "mx_map_boundary_un_3",
    "en": "Map: Armistice or international boundary_unistrative line",
    "ru": ""
  },
  {
    "id": "mx_map_boundary_un_4",
    "en": "Map: Other line of separation",
    "ru": ""
  },
  {
    "id": "mx_map_boundary_un_8",
    "en": "Map: Autonomous region boundary",
    "ru": ""
  },
  {
    "id": "mx_map_boundary_un_9",
    "en": "Map: Sovereign base limit",
    "ru": ""
  },
  {
    "id": "mx_map_boundary_osm_subnational",
    "en": "Map: Subnational boundaries",
    "ru": ""
  },
  {
    "id": "mx_map_text_place",
    "en": "Map: place text",
    "ru": ""
  },
  {
    "id": "mx_map_text_place_outline",
    "en": "Map: place text outline",
    "ru": ""
  },
  {
    "id": "mx_map_text_road",
    "en": "Map: road text",
    "ru": ""
  },
  {
    "id": "mx_map_text_road_outline",
    "en": "Map: road text outline",
    "ru": ""
  },
  {
    "id": "mx_map_text_water",
    "en": "Map: water body text",
    "ru": ""
  },
  {
    "id": "mx_map_text_water_outline",
    "en": "Map: water body text outline",
    "ru": ""
  },
  {
    "id": "list_publishers",
    "en": "List of publishers",
    "ru": ""
  },
  {
    "id": "list_members",
    "en": "List of members",
    "ru": ""
  },
  {
    "id": "list_admins",
    "en": "List of administrators",
    "ru": ""
  },
  {
    "id": "list_contacts",
    "en": "Contact person",
    "ru": ""
  },
  {
    "id": "new_publishers",
    "en": "New publishers",
    "ru": ""
  },
  {
    "id": "new_members",
    "en": "New members",
    "ru": ""
  },
  {
    "id": "new_admins",
    "en": "New administrators",
    "ru": ""
  },
  {
    "id": "new_contacts",
    "en": "New admin. contacts",
    "ru": ""
  },
  {
    "id": "rem_publishers",
    "en": "Publishers removed",
    "ru": ""
  },
  {
    "id": "rem_members",
    "en": "Members removed",
    "ru": ""
  },
  {
    "id": "rem_admins",
    "en": "Administrators removed",
    "ru": ""
  },
  {
    "id": "rem_contacts",
    "en": "Contacts removed",
    "ru": ""
  },
  {
    "id": "no_changes",
    "en": "No change",
    "ru": ""
  },
  {
    "id": "roles_updated",
    "en": "Roles updated",
    "ru": ""
  },
  {
    "id": "roles",
    "en": "Roles",
    "ru": ""
  },
  {
    "id": "success_update",
    "en": "Update successful",
    "ru": ""
  },
  {
    "id": "error_roles_no_admins",
    "en": "Require at least one admin",
    "ru": ""
  },
  {
    "id": "error_views_need_data",
    "en": "Deletion of a source disabled because at least one view depends on it",
    "ru": ""
  },
  {
    "id": "error_views_need_publishers",
    "en": "At least one view needs this source to be available for publishers. Update disabled.",
    "ru": ""
  },
  {
    "id": "error_roles_removed_self",
    "en": "You can't remove yourself from admin group",
    "ru": ""
  },
  {
    "id": "project_enable_public",
    "en": "This project is public. It will be listed in the catalog of projects. All public views published in this project will be readable for everyone.",
    "ru": ""
  },
  {
    "id": "project_enable_join",
    "en": "Allow non-members to request a membership to this project.",
    "ru": ""
  },
  {
    "id": "project_state_key",
    "en": "Identifier",
    "ru": ""
  },
  {
    "id": "project_save_views_state",
    "en": "Save views state",
    "ru": ""
  },
  {
    "id": "project_roles_modal_title",
    "en": "Roles administration",
    "ru": ""
  },
  {
    "id": "project_alias_name",
    "en": "Alias of the project",
    "ru": ""
  },
  {
    "id": "project_alias_name_desc",
    "en": "Minimum 1, maximum 30 lower case whithin ASCII characters [a-z], numbers [0-9], dashes [-] and underscores allowed [_]",
    "ru": ""
  },
  {
    "id": "error_project_alias_not_valid",
    "en": "Project alias not valid or already taken",
    "ru": ""
  },
  {
    "id": "project_access_denied",
    "en": "Access denied. You cannot access the requested project",
    "ru": ""
  },
  {
    "id": "project_delete_confirm_title",
    "en": "Write the project name you want to delete",
    "ru": ""
  },
  {
    "id": "project_invite_modal_title",
    "en": "Invite a new member",
    "ru": ""
  },
  {
    "id": "btn_show_invite_member",
    "en": "Invite a new member",
    "ru": ""
  },
  {
    "id": "project_invite_message_compose",
    "en": "Compose invite email",
    "ru": ""
  },
  {
    "id": "project_invite_message_sent",
    "en": "Email sent.",
    "ru": ""
  },
  {
    "id": "project_invite_message_tips",
    "en": "The tag <link> will be replaced by an encrypted link.",
    "ru": ""
  },
  {
    "id": "project_invite_message",
    "en": "Hi!\\nI would like to invite you as a member to the project <projectname> in MapX.\\nPlease click on the provided link to confirm.\\n<link>\\nThe administrator of the project <projectname>",
    "ru": ""
  },
  {
    "id": "project_invite_message_confirm",
    "en": "Hi!\\n\\nThanks for reaching us.\\nTo confirm your membership to the project <projectname> in MapX, please click on the following link:\\n<link>\\nBest regards,\\nThe administrator of the project <projectname>",
    "ru": ""
  },
  {
    "id": "project_countries_highlight",
    "en": "Countries to be highlighted on the map",
    "ru": ""
  },
  {
    "id": "project_search_values",
    "en": "Search projects",
    "ru": ""
  },
  {
    "id": "project_saved",
    "en": "Project saved",
    "ru": ""
  },
  {
    "id": "project_created",
    "en": "Project %1$s created",
    "ru": ""
  },
  {
    "id": "project_deleted",
    "en": "Project deleted",
    "ru": ""
  },
  {
    "id": "project_delete_analyze",
    "en": "Analysing, please wait...",
    "ru": ""
  },
  {
    "id": "project_delete_number_of_sources",
    "en": "Number of sources to delete",
    "ru": ""
  },
  {
    "id": "project_delete_number_of_views",
    "en": "Number of views to delete",
    "ru": ""
  },
  {
    "id": "project_delete_title",
    "en": "Project deletion",
    "ru": ""
  },
  {
    "id": "project_new_title",
    "en": "Title of the project",
    "ru": ""
  },
  {
    "id": "project_list",
    "en": "List of projects",
    "ru": ""
  },
  {
    "id": "project_list_select_desc",
    "en": "Click on a project name to access it. If you are not member of a project, you can ask to join it by clicking the join button ",
    "ru": ""
  },
  {
    "id": "project_title",
    "en": "Title",
    "ru": ""
  },
  {
    "id": "project_description",
    "en": "Description",
    "ru": ""
  },
  {
    "id": "project_settings",
    "en": "Project settings",
    "ru": ""
  },
  {
    "id": "project_map_pos_set",
    "en": "Initial map position",
    "ru": ""
  },
  {
    "id": "project_map_pos_get",
    "en": "Use current map parameters",
    "ru": ""
  },
  {
    "id": "map_fit_to_bounds",
    "en": "Use extent to center the map",
    "ru": ""
  },
  {
    "id": "map_zoom",
    "en": "Zoom",
    "ru": ""
  },
  {
    "id": "map_longitude_center",
    "en": "Longitude at center",
    "ru": ""
  },
  {
    "id": "map_latitude_center",
    "en": "Latitude at center",
    "ru": ""
  },
  {
    "id": "map_pitch",
    "en": "Camera pitch",
    "ru": ""
  },
  {
    "id": "map_bearing",
    "en": "Camera bearing",
    "ru": ""
  },
  {
    "id": "map_north_max",
    "en": "Max north latitude",
    "ru": ""
  },
  {
    "id": "map_south_max",
    "en": "Max south latitude",
    "ru": ""
  },
  {
    "id": "map_east_max",
    "en": "Max east longitude",
    "ru": ""
  },
  {
    "id": "map_west_max",
    "en": "Max west longitude",
    "ru": ""
  },
  {
    "id": "view_public_valid",
    "en": "This view is publicly available",
    "ru": ""
  },
  {
    "id": "view_public_not_valid",
    "en": "This view is publicly available \n with incomplete metadata",
    "ru": ""
  },
  {
    "id": "view_editable",
    "en": "You have editor rights for this view",
    "ru": ""
  },
  {
    "id": "view_locked",
    "en": "You do not have editor rights",
    "ru": ""
  },
  {
    "id": "txt_too_short_min_3",
    "en": "Text too short, minimum 3 characters",
    "ru": ""
  },
  {
    "id": "txt_email_not_valid",
    "en": "Email not valid",
    "ru": ""
  },
  {
    "id": "project_request_membership_message",
    "en": "Hi!\\nPlease add me to the project <projectname>. \\nBest regards,\\nA motivated future member\\n",
    "ru": ""
  },
  {
    "id": "project_request_membership_message_compose",
    "en": "Membership request",
    "ru": ""
  },
  {
    "id": "project_request_membership_message_recap",
    "en": "A membership request from <from> has been received. \\nMessage : \\n-\\n<msg>\\n-\\nConfirmation : <link>\\nData : <data>\\n",
    "ru": ""
  },
  {
    "id": "project_request_membership_message_sent",
    "en": "Your request has been sent to the project administrator, you will receive a confirmation email in the coming days. Check your inbox for an email from the MapX bot and click the link to access the project!",
    "ru": ""
  },
  {
    "id": "update_app_msg",
    "en": "MapX has been updated, this page will be reloaded now.",
    "ru": ""
  },
  {
    "id": "btn_clear_cache",
    "en": "Clear cached data",
    "ru": ""
  },
  {
    "id": "title_utilities",
    "en": "Utilities",
    "ru": ""
  },
  {
    "id": "update_app_title",
    "en": "Update",
    "ru": ""
  },
  {
    "id": "btn_install_update",
    "en": "Install and reload",
    "ru": ""
  },
  {
    "id": "tbl_views_depending_source",
    "en": "Table of views depending on the source",
    "ru": ""
  },
  {
    "id": "btn_validate_metadata",
    "en": "In depth validation",
    "ru": ""
  },
  {
    "id": "validate_meta_title",
    "en": "Metadata validation",
    "ru": ""
  },
  {
    "id": "validate_meta_no_issue",
    "en": "Metadata are valid.",
    "ru": ""
  },
  {
    "id": "validate_meta_attribute",
    "en": "Attributes",
    "ru": ""
  },
  {
    "id": "validate_meta_invalid_attribute",
    "en": "Invalid attribute description entry",
    "ru": ""
  },
  {
    "id": "validate_meta_abstract",
    "en": "Abstract",
    "ru": ""
  },
  {
    "id": "validate_meta_invalid_abstract",
    "en": "Invalid abstract",
    "ru": ""
  },
  {
    "id": "validate_meta_title",
    "en": "Title",
    "ru": ""
  },
  {
    "id": "validate_meta_invalid_title",
    "en": "Invalid title",
    "ru": ""
  },
  {
    "id": "validate_meta_keyword",
    "en": "Keywords",
    "ru": ""
  },
  {
    "id": "validate_meta_no_keyword",
    "en": "Missing keywords",
    "ru": ""
  },
  {
    "id": "validate_meta_invalid_keyword",
    "en": "Invalid keywords",
    "ru": ""
  },
  {
    "id": "validate_meta_contact",
    "en": "Contacts",
    "ru": ""
  },
  {
    "id": "validate_meta_no_contact",
    "en": "Missing contact",
    "ru": ""
  },
  {
    "id": "validate_meta_invalid_contact_email",
    "en": "Invalid contact email",
    "ru": ""
  },
  {
    "id": "validate_meta_issuance",
    "en": "Issuance",
    "ru": ""
  },
  {
    "id": "validate_meta_invalid_issuance_periodicity",
    "en": "Invalid periodicity",
    "ru": ""
  },
  {
    "id": "validate_meta_invalid_issuance_released_at",
    "en": "Invalid date of release",
    "ru": ""
  },
  {
    "id": "validate_meta_invalid_issuance_modified_at",
    "en": "Invalid date of modification",
    "ru": ""
  },
  {
    "id": "validate_meta_license",
    "en": "License",
    "ru": ""
  },
  {
    "id": "validate_meta_no_license",
    "en": "Missing license",
    "ru": ""
  },
  {
    "id": "validate_meta_invalid_license",
    "en": "Invalid license",
    "ru": ""
  },
  {
    "id": "validate_meta_source",
    "en": "Source",
    "ru": ""
  },
  {
    "id": "validate_meta_no_source",
    "en": "Source missing",
    "ru": ""
  },
  {
    "id": "validate_meta_invalid_source",
    "en": "Invalid source",
    "ru": ""
  },
  {
    "id": "validate_meta_invalid_external_link",
    "en": "Invalid external link",
    "ru": ""
  },
  {
    "id": "source_last_editor_email",
    "en": "Email of the last editor",
    "ru": ""
  },
  {
    "id": "additional_doc_desc",
    "en": "If any, list of additional documents",
    "ru": ""
  },
  {
    "id": "additional_doc_items_desc",
    "en": "Related documents such as technical information about a dataset",
    "ru": ""
  },
  {
    "id": "additional_doc_items_title",
    "en": "List of annexes",
    "ru": ""
  },
  {
    "id": "additional_doc_item_title",
    "en": "Document",
    "ru": ""
  },
  {
    "id": "additional_doc_item_url",
    "en": "URL to the document",
    "ru": ""
  },
  {
    "id": "additional_doc_title",
    "en": "Annexes",
    "ru": ""
  },
  {
    "id": "annually",
    "en": "Data is updated every year",
    "ru": ""
  },
  {
    "id": "as_needed",
    "en": "Data is updated as deemed necessary",
    "ru": ""
  },
  {
    "id": "attribute_item_title",
    "en": "Attribute",
    "ru": ""
  },
  {
    "id": "attribute_name_title",
    "en": "Attribute name",
    "ru": ""
  },
  {
    "id": "attributes_list_title",
    "en": "Attributes list",
    "ru": ""
  },
  {
    "id": "attributes_desc_title",
    "en": "Attributes description",
    "ru": ""
  },
  {
    "id": "attributes_desc_desc",
    "en": "Description of the attributes contained in the data",
    "ru": ""
  },
  {
    "id": "attribute_desc_item_title",
    "en": "Description",
    "ru": ""
  },
  {
    "id": "attributes_alias_title",
    "en": "Alias for attributes names",
    "ru": ""
  },
  {
    "id": "attributes_alias_desc",
    "en": "Set attributes short names (alias)",
    "ru": ""
  },
  {
    "id": "attribute_alias_item_title",
    "en": "Alias",
    "ru": ""
  },
  {
    "id": "biannually",
    "en": "Data is updated twice each year",
    "ru": ""
  },
  {
    "id": "confirm_source_remove",
    "en": "Are you sure to delete the source with all related views and metadata ? This can't be undone",
    "ru": ""
  },
  {
    "id": "contact_address",
    "en": "Contact address",
    "ru": ""
  },
  {
    "id": "contact_desc",
    "en": "Information about people or organisation related to this data",
    "ru": ""
  },
  {
    "id": "contact_email",
    "en": "Contact email",
    "ru": ""
  },
  {
    "id": "contact_function",
    "en": "Function",
    "ru": ""
  },
  {
    "id": "contact_function_desc",
    "en": "Name of the contact function, e.g. Administrator, Publisher",
    "ru": ""
  },
  {
    "id": "contact_item_title",
    "en": "Contact",
    "ru": ""
  },
  {
    "id": "contact_list_title",
    "en": "List of contacts",
    "ru": ""
  },
  {
    "id": "contact_name",
    "en": "Contact name",
    "ru": ""
  },
  {
    "id": "contact_title",
    "en": "Contacts",
    "ru": ""
  },
  {
    "id": "continual",
    "en": "Data is repeatedly and frequently updated",
    "ru": ""
  },
  {
    "id": "daily",
    "en": "Data is updated each day",
    "ru": ""
  },
  {
    "id": "fortnightly",
    "en": "Data is updated every two weeks",
    "ru": ""
  },
  {
    "id": "irregular",
    "en": "Data is updated in intervals that are uneven in duration",
    "ru": ""
  },
  {
    "id": "lang_desc",
    "en": "Language(s) used in content",
    "ru": ""
  },
  {
    "id": "lang_item_title",
    "en": "Language",
    "ru": ""
  },
  {
    "id": "lang_list_desc",
    "en": "Two letters code of languages",
    "ru": ""
  },
  {
    "id": "lang_list_title",
    "en": "List of languages",
    "ru": ""
  },
  {
    "id": "lang_title",
    "en": "Language",
    "ru": ""
  },
  {
    "id": "license_allow_download",
    "en": "Allow download source",
    "ru": ""
  },
  {
    "id": "license_desc",
    "en": "If any, description of the data licenses",
    "ru": ""
  },
  {
    "id": "license_item_title",
    "en": "License",
    "ru": ""
  },
  {
    "id": "license_list_desc",
    "en": "Name and/or description of the licence",
    "ru": ""
  },
  {
    "id": "license_list_title",
    "en": "List of licences",
    "ru": ""
  },
  {
    "id": "license_name",
    "en": "Name",
    "ru": ""
  },
  {
    "id": "license_text",
    "en": "Text",
    "ru": ""
  },
  {
    "id": "license_title",
    "en": "Licensing",
    "ru": ""
  },
  {
    "id": "maintainer",
    "en": "Maintainer",
    "ru": ""
  },
  {
    "id": "monthly",
    "en": "Data is updated each month",
    "ru": ""
  },
  {
    "id": "msg_error_duplicate",
    "en": "This source already exists and is available for you",
    "ru": ""
  },
  {
    "id": "msg_error_import",
    "en": "Data was not imported",
    "ru": ""
  },
  {
    "id": "msg_process_wait",
    "en": "Data is processed, please wait",
    "ru": ""
  },
  {
    "id": "msg_success_delete",
    "en": "Source successfully removed",
    "ru": ""
  },
  {
    "id": "msg_success_import",
    "en": "Data imported successfully",
    "ru": ""
  },
  {
    "id": "msg_success_update",
    "en": "Meta data successfully updated",
    "ru": ""
  },
  {
    "id": "not_planned",
    "en": "There are no plans to update the data",
    "ru": ""
  },
  {
    "id": "optional_view_show_attribute_preview",
    "en": "Show a summary of the attributes names and values",
    "ru": ""
  },
  {
    "id": "optional_view_text",
    "en": "Select an attribute from the source to create a simple view or click on finish to end the importation",
    "ru": ""
  },
  {
    "id": "optional_view_title",
    "en": "Optional creation of a new view",
    "ru": ""
  },
  {
    "id": "origin_desc",
    "en": "Origin of the data and how to retrieve it",
    "ru": ""
  },
  {
    "id": "origin_homepage_desc",
    "en": "Homepage for the data",
    "ru": ""
  },
  {
    "id": "origin_homepage_item_title",
    "en": "Homepage (URL)",
    "ru": ""
  },
  {
    "id": "origin_homepage_title",
    "en": "Homepage",
    "ru": ""
  },
  {
    "id": "origin_source_is_full_request_title",
    "en": "The url contain a request to retrieve the data automatically",
    "ru": ""
  },
  {
    "id": "origin_sources_desc",
    "en": "Method to retrieve the data",
    "ru": ""
  },
  {
    "id": "origin_sources_list",
    "en": "List of sources",
    "ru": ""
  },
  {
    "id": "origin_sources_title",
    "en": "Sources",
    "ru": ""
  },
  {
    "id": "origin_source_title",
    "en": "Source",
    "ru": ""
  },
  {
    "id": "origin_source_url_title",
    "en": "URL",
    "ru": ""
  },
  {
    "id": "origin_title",
    "en": "Source",
    "ru": ""
  },
  {
    "id": "other",
    "en": "Other",
    "ru": ""
  },
  {
    "id": "quarterly",
    "en": "Data is updated every three months",
    "ru": ""
  },
  {
    "id": "schema_desc",
    "en": "Metadata editor for MapX sources.",
    "ru": ""
  },
  {
    "id": "schema_title",
    "en": "MapX metadata",
    "ru": ""
  },
  {
    "id": "schema_story_views_activate",
    "en": "Views to activate",
    "ru": ""
  },
  {
    "id": "schema_story_slide_classes",
    "en": "Slide classes",
    "ru": ""
  },
  {
    "id": "schema_story_slide_classes_name",
    "en": "Class names",
    "ru": ""
  },
  {
    "id": "schema_story_slide_allow_scroll",
    "en": "Allow scrolling",
    "ru": ""
  },
  {
    "id": "schema_story_slide_allow_scroll_desc",
    "en": "If the slide content goes outside the container, a scrollbar will be displayed.",
    "ru": ""
  },
  {
    "id": "schema_story_slide_base_txt_size_px",
    "en": "Base text size in pixels",
    "ru": ""
  },
  {
    "id": "schema_story_slide_effects",
    "en": "Effects",
    "ru": ""
  },
  {
    "id": "schema_story_slide_effect_start",
    "en": "Start",
    "ru": ""
  },
  {
    "id": "schema_story_slide_effect_end",
    "en": "End",
    "ru": ""
  },
  {
    "id": "schema_story_slide_effect_offset",
    "en": "Offset",
    "ru": ""
  },
  {
    "id": "schema_story_slide_effect_factor",
    "en": "Factor",
    "ru": ""
  },
  {
    "id": "schema_story_slide_effect_type",
    "en": "Type",
    "ru": ""
  },
  {
    "id": "schema_story_slide_name",
    "en": "Slide name",
    "ru": ""
  },
  {
    "id": "schema_story_map_anim_duration",
    "en": "Animation duration [ms]",
    "ru": ""
  },
  {
    "id": "schema_story_map_anim_duration_desc",
    "en": "Change the total animation duration",
    "ru": ""
  },
  {
    "id": "schema_story_map_anim_traj_method",
    "en": "Trajectory method",
    "ru": ""
  },
  {
    "id": "schema_story_map_anim_traj_method_desc",
    "en": "Set the traveling method of the camera during the animation",
    "ru": ""
  },
  {
    "id": "schema_story_map_anim_fun",
    "en": "Animation function",
    "ru": ""
  },
  {
    "id": "schema_story_map_anim_fun_desc",
    "en": "Change the default animation function. Ease the start and/or end of the animation.",
    "ru": ""
  },
  {
    "id": "schema_story_map_anim_fun_exp",
    "en": "Animation function exponent",
    "ru": ""
  },
  {
    "id": "schema_story_map_anim_fun_exp_desc",
    "en": "Change the default function exponent. This will amplify or reduce the rate of the easing.",
    "ru": ""
  },
  {
    "id": "schema_story_map_anim",
    "en": "Map animation",
    "ru": ""
  },
  {
    "id": "schema_story_autoplay_timeout",
    "en": "Timeout [ms]",
    "ru": ""
  },
  {
    "id": "schema_story_autoplay_timeout_desc",
    "en": "Waiting time before going to the next step.",
    "ru": ""
  },
  {
    "id": "schema_story_autoplay_transition",
    "en": "Transition [ms]",
    "ru": ""
  },
  {
    "id": "schema_story_autoplay_transition_desc",
    "en": "Duration of the transition between steps.",
    "ru": ""
  },
  {
    "id": "schema_story_autoplay",
    "en": "Autoplay settings",
    "ru": ""
  },
  {
    "id": "schema_story_step_name",
    "en": "Step name",
    "ru": ""
  },
  {
    "id": "schema_story_screen_res",
    "en": "Screen resolution",
    "ru": ""
  },
  {
    "id": "schema_story_screen_res_desc",
    "en": "Base resolution of the page during a story map. It will automatically scale to fit the screen and preserve content formating.",
    "ru": ""
  },
  {
    "id": "schema_story_settings",
    "en": "Settings",
    "ru": ""
  },
  {
    "id": "button_legend_title",
    "en": "Legends",
    "ru": ""
  },
  {
    "id": "button_legend_button",
    "en": "Legends",
    "ru": ""
  },
  {
    "id": "button_issues",
    "en": "Issues",
    "ru": ""
  },
  {
    "id": "select_optional_view_attribute",
    "en": "Select attribute",
    "ru": ""
  },
  {
    "id": "spatial_bbx_desc",
    "en": "Spatial bounding box of the data using latitude and longitude",
    "ru": ""
  },
  {
    "id": "spatial_bbx_lat_max",
    "en": "Max. latitude",
    "ru": ""
  },
  {
    "id": "spatial_bbx_lat_min",
    "en": "Min. latitude",
    "ru": ""
  },
  {
    "id": "spatial_bbx_lng_max",
    "en": "Max. longitude",
    "ru": ""
  },
  {
    "id": "spatial_bbx_lng_min",
    "en": "Min. longitude",
    "ru": ""
  },
  {
    "id": "spatial_bbx_title",
    "en": "Bounding box",
    "ru": ""
  },
  {
    "id": "spatial_desc",
    "en": "Description of the data using spatial reference: bounding box, and spatial reference system (SRS)",
    "ru": ""
  },
  {
    "id": "spatial_srs_code",
    "en": "Code of the SRS",
    "ru": ""
  },
  {
    "id": "spatial_srs_desc",
    "en": "Description of the spatial reference system",
    "ru": ""
  },
  {
    "id": "spatial_srs_desc_url",
    "en": "URL to the SRS code definition",
    "ru": ""
  },
  {
    "id": "spatial_srs_title",
    "en": "Spatial reference system",
    "ru": ""
  },
  {
    "id": "spatial_title",
    "en": "Spatial",
    "ru": ""
  },
  {
    "id": "summary_attribute",
    "en": "Summary ",
    "ru": ""
  },
  {
    "id": "target_desc",
    "en": "Modality and restriction of access to the data",
    "ru": ""
  },
  {
    "id": "target_role_item_title",
    "en": "Role",
    "ru": ""
  },
  {
    "id": "target_roles_read_title",
    "en": "Roles allowed to read",
    "ru": ""
  },
  {
    "id": "target_roles_admin_title",
    "en": "Roles allowed to manage",
    "ru": ""
  },
  {
    "id": "target_roles_get_title",
    "en": "Roles allowed to download",
    "ru": ""
  },
  {
    "id": "target_roles_list_title",
    "en": "List of roles",
    "ru": ""
  },
  {
    "id": "target_roles_title",
    "en": "Roles",
    "ru": ""
  },
  {
    "id": "target_title",
    "en": "Access",
    "ru": ""
  },
  {
    "id": "temporal_desc",
    "en": "Description of the dataset using temporal references: periodicity, initial release, update and range",
    "ru": ""
  },
  {
    "id": "temporal_issuance_desc",
    "en": "Description if the data issuance",
    "ru": ""
  },
  {
    "id": "temporal_issuance_title",
    "en": "Issuance",
    "ru": ""
  },
  {
    "id": "temporal_periodicity",
    "en": "Periodicity",
    "ru": ""
  },
  {
    "id": "temporal_periodicity_desc",
    "en": "Frenquency with wich data is published or updated",
    "ru": ""
  },
  {
    "id": "temporal_range_desc",
    "en": "The temporal range of the data",
    "ru": ""
  },
  {
    "id": "temporal_range_end",
    "en": "End",
    "ru": ""
  },
  {
    "id": "temporal_range_start",
    "en": "Start",
    "ru": ""
  },
  {
    "id": "temporal_range_timeless",
    "en": "There is no time range for this data",
    "ru": ""
  },
  {
    "id": "temporal_range_title",
    "en": "Range",
    "ru": ""
  },
  {
    "id": "temporal_release_desc",
    "en": "Date of formal issuance",
    "ru": ""
  },
  {
    "id": "temporal_release_title",
    "en": "Release date",
    "ru": ""
  },
  {
    "id": "temporal_title",
    "en": "Temporal",
    "ru": ""
  },
  {
    "id": "temporal_update_desc",
    "en": "Date of the latest update",
    "ru": ""
  },
  {
    "id": "temporal_update_title",
    "en": "Last update",
    "ru": ""
  },
  {
    "id": "textual_desc",
    "en": "Textual description of the data using title, abstract and tags",
    "ru": ""
  },
  {
    "id": "textual_desc_notes",
    "en": "Additional notes",
    "ru": ""
  },
  {
    "id": "textual_desc_abstract",
    "en": "Abstract",
    "ru": ""
  },
  {
    "id": "textual_desc_title",
    "en": "Title",
    "ru": ""
  },
  {
    "id": "textual_keyword_desc",
    "en": "Keywords (or tags) help users discover your dataset. Please include terms that would be used by technical and non-technical users.",
    "ru": ""
  },
  {
    "id": "textual_keyword_item_title",
    "en": "Keyword",
    "ru": ""
  },
  {
    "id": "textual_keywords_title",
    "en": "Keywords list",
    "ru": ""
  },
  {
    "id": "textual_keyword_title",
    "en": "Keywords",
    "ru": ""
  },
  {
    "id": "textual_title",
    "en": "Textual",
    "ru": ""
  },
  {
    "id": "unknown",
    "en": "Frequency of maintenance for the data is not known",
    "ru": ""
  },
  {
    "id": "weekly",
    "en": "Data is updated on a weekly basis",
    "ru": ""
  },
  {
    "id": "meta_display_source_title",
    "en": "Metadata of the source",
    "ru": ""
  },
  {
    "id": "meta_display_view_title",
    "en": "Summary of the view metadata",
    "ru": ""
  },
  {
    "id": "meta_last_editor_id",
    "en": "Editor id",
    "ru": ""
  },
  {
    "id": "meta_all_editor_id",
    "en": "Id of all editors",
    "ru": ""
  },
  {
    "id": "meta_view_modal_title",
    "en": "Metadata of the view",
    "ru": ""
  },
  {
    "id": "meta_view_table_summary_title",
    "en": "Summary",
    "ru": ""
  },
  {
    "id": "meta_view_raster_meta",
    "en": "Metadata Entry",
    "ru": ""
  },
  {
    "id": "meta_view_table_editors_title",
    "en": "Changes overview",
    "ru": ""
  },
  {
    "id": "meta_view_table_editors_changes",
    "en": "N. of changes",
    "ru": ""
  },
  {
    "id": "meta_view_table_editors_email",
    "en": "Editor",
    "ru": ""
  },
  {
    "id": "meta_view_table_editors_current",
    "en": "Latest edit",
    "ru": ""
  },
  {
    "id": "meta_view_title",
    "en": "View title",
    "ru": ""
  },
  {
    "id": "meta_view_abstract",
    "en": "Abstract",
    "ru": ""
  },
  {
    "id": "meta_view_stat_n_add",
    "en": "Number of viewing",
    "ru": ""
  },
  {
    "id": "meta_view_stat_n_distinct_user",
    "en": "Number of distinct users",
    "ru": ""
  },
  {
    "id": "meta_source_title",
    "en": "Title",
    "ru": ""
  },
  {
    "id": "meta_source_abstract",
    "en": "Abstract",
    "ru": ""
  },
  {
    "id": "meta_source_notes",
    "en": "Notes",
    "ru": ""
  },
  {
    "id": "meta_source_keywords",
    "en": "Keywords",
    "ru": ""
  },
  {
    "id": "meta_source_languages",
    "en": "Languages used in the data",
    "ru": ""
  },
  {
    "id": "meta_source_contacts",
    "en": "Contacts list",
    "ru": ""
  },
  {
    "id": "meta_source_periodicity",
    "en": "Periodicity",
    "ru": ""
  },
  {
    "id": "meta_source_released_at",
    "en": "Date of release",
    "ru": ""
  },
  {
    "id": "meta_source_modified_at",
    "en": "Date of modification",
    "ru": ""
  },
  {
    "id": "meta_source_start_at",
    "en": "Data values starting date",
    "ru": ""
  },
  {
    "id": "meta_source_end_at",
    "en": "Data values ending date",
    "ru": ""
  },
  {
    "id": "meta_source_is_timeless",
    "en": "Data without temporal values",
    "ru": ""
  },
  {
    "id": "meta_view_projects_titles",
    "en": "Also published in those projects",
    "ru": ""
  },
  {
    "id": "meta_view_project_title",
    "en": "Original project",
    "ru": ""
  },
  {
    "id": "meta_view_projects",
    "en": "Projects",
    "ru": ""
  },
  {
    "id": "meta_view_id",
    "en": "View id",
    "ru": ""
  },
  {
    "id": "meta_view_collections",
    "en": "Collections",
    "ru": ""
  },
  {
    "id": "meta_view_date_modified",
    "en": "Modification date",
    "ru": ""
  },
  {
    "id": "meta_view_date_created",
    "en": "Creation date",
    "ru": ""
  },
  {
    "id": "meta_view_editor",
    "en": "Editor",
    "ru": ""
  },
  {
    "id": "meta_view_editors",
    "en": "Groups with editing access",
    "ru": ""
  },
  {
    "id": "meta_view_readers",
    "en": "Groups with reading access",
    "ru": ""
  },
  {
    "id": "meta_view_type",
    "en": "Type",
    "ru": ""
  },
  {
    "id": "meta_view_table_summary_title",
    "en": "Summary of the view",
    "ru": ""
  },
  {
    "id": "meta_source_id",
    "en": "Source id",
    "ru": ""
  },
  {
    "id": "meta_source_table_summary_title",
    "en": "Summary of the source",
    "ru": ""
  },
  {
    "id": "meta_source_homepage",
    "en": "Source homepage",
    "ru": ""
  },
  {
    "id": "meta_source_url_download",
    "en": "Download original source",
    "ru": ""
  },
  {
    "id": "meta_source_url_annexes",
    "en": "Download annexes",
    "ru": ""
  },
  {
    "id": "meta_source_integrity_score",
    "en": "Integrity score",
    "ru": ""
  },
  {
    "id": "meta_source_time_range",
    "en": "Temporal range",
    "ru": ""
  },
  {
    "id": "meta_source_time_range_min",
    "en": "From",
    "ru": ""
  },
  {
    "id": "meta_source_time_range_max",
    "en": "To",
    "ru": ""
  },
  {
    "id": "dont_know",
    "en": "I don't know",
    "ru": ""
  },
  {
    "id": "yes",
    "en": "Yes",
    "ru": ""
  },
  {
    "id": "no",
    "en": "No",
    "ru": ""
  },
  {
    "id": "partial",
    "en": "Partially",
    "ru": ""
  },
  {
    "id": "wms_select_reviewed_service",
    "en": "Select stored service",
    "ru": ""
  },
  {
    "id": "wms_select_layer",
    "en": "Select layer",
    "ru": ""
  },
  {
    "id": "wms_input_service_url",
    "en": "Enter service URL",
    "ru": ""
  },
  {
    "id": "wms_btn_generate_url",
    "en": "Update generated URL ( tiles server, legends )",
    "ru": ""
  },
  {
    "id": "wms_btn_get_layers",
    "en": "Update layer list",
    "ru": ""
  },
  {
    "id": "app_maintenance_title",
    "en": "Maintenance",
    "ru": ""
  },
  {
    "id": "app_maintenance_text",
    "en": "MapX is currently unavailable due to server maintenance. </br> Come back later in the day !  </br> </br> Sincerely, your MapX team",
    "ru": ""
  },
  {
    "id": "pk_panel_options",
    "en": "Display options",
    "ru": ""
  },
  {
    "id": "pk_tab_settings",
    "en": "Palette tool",
    "ru": ""
  },
  {
    "id": "pk_tab_palettes",
    "en": "Palettes",
    "ru": ""
  },
  {
    "id": "pk_tab_edit_json",
    "en": "Edit JSON",
    "ru": ""
  },
  {
    "id": "pk_btn_add",
    "en": "Add",
    "ru": ""
  },
  {
    "id": "pk_btn_close",
    "en": "Close",
    "ru": ""
  },
  {
    "id": "pk_slider_n_hue_rotation",
    "en": "Number of hue rotation",
    "ru": ""
  },
  {
    "id": "pk_slider_n_colors",
    "en": "Number of colors",
    "ru": ""
  },
  {
    "id": "pk_slider_hue_shift",
    "en": "Hue shift",
    "ru": ""
  },
  {
    "id": "pk_slider_colors",
    "en": "Colors space",
    "ru": ""
  },
  {
    "id": "pk_slider_saturation",
    "en": "Saturation",
    "ru": ""
  },
  {
    "id": "pk_slider_luminosity",
    "en": "Luminosity",
    "ru": ""
  },
  {
    "id": "pk_slider_randomize",
    "en": "Shuffle",
    "ru": ""
  },
  {
    "id": "pk_slider_reverse",
    "en": "Reverse",
    "ru": ""
  },
  {
    "id": "pk_slider_diverge",
    "en": "Diverge",
    "ru": ""
  },
  {
    "id": "pk_btn_set_default_palette",
    "en": "Use the default palette",
    "ru": ""
  },
  {
    "id": "btn_opt_meta",
    "en": "Enable draw mode",
    "ru": ""
  },
  {
    "id": "draft_recover_modal_title",
    "en": "Data recovery",
    "ru": ""
  },
  {
    "id": "draft_recover_use_most_recent",
    "en": "Use the most recent",
    "ru": ""
  },
  {
    "id": "draft_recover_cancel",
    "en": "Cancel",
    "ru": ""
  },
  {
    "id": "draft_recover_preview_diff",
    "en": "Preview differences",
    "ru": ""
  },
  {
    "id": "draft_recover_last_saved_date",
    "en": "Date of the last saved version",
    "ru": ""
  },
  {
    "id": "draft_recover_recovered_date",
    "en": "Date of the recovered version",
    "ru": ""
  },
  {
    "id": "draft_recover_diffs",
    "en": "Differences",
    "ru": ""
  },
  {
    "id": "draft_recover_summary_title",
    "en": "Summary",
    "ru": ""
  },
  {
    "id": "api_download_ready",
    "en": "Process done, the data is available for download : ",
    "ru": ""
  },
  {
    "id": "api_upload_ready",
    "en": "Process done, the data will be available in source list.",
    "ru": ""
  },
  {
    "id": "api_upload_done_wait_db",
    "en": "Upload done. Importation in DB, please wait, this could take multiple minutes for complex layers. Please be patient.",
    "ru": ""
  },
  {
    "id": "api_download_btn",
    "en": "click here",
    "ru": ""
  },
  {
    "id": "api_progress_title",
    "en": "Progress",
    "ru": ""
  },
  {
    "id": "api_log_title",
    "en": "Log",
    "ru": ""
  },
  {
    "id": "error_notset",
    "en": "Property must be set",
    "ru": ""
  },
  {
    "id": "error_notempty",
    "en": "Value required",
    "ru": ""
  },
  {
    "id": "error_enum",
    "en": "Value must be one of the enumerated values",
    "ru": ""
  },
  {
    "id": "error_anyOf",
    "en": "Value must validate against at least one of the provided schemas",
    "ru": ""
  },
  {
    "id": "error_oneOf",
    "en": "Value must validate against exactly one of the provided schemas. It currently validates against {{0}} of the schemas.",
    "ru": ""
  },
  {
    "id": "error_not",
    "en": "Value must not validate against the provided schema",
    "ru": ""
  },
  {
    "id": "error_type_union",
    "en": "Value must be one of the provided types",
    "ru": ""
  },
  {
    "id": "error_type",
    "en": "Value must be of type {{0}}",
    "ru": ""
  },
  {
    "id": "error_disallow_union",
    "en": "Value must not be one of the provided disallowed types",
    "ru": ""
  },
  {
    "id": "error_disallow",
    "en": "Value must not be of type {{0}}",
    "ru": ""
  },
  {
    "id": "error_multipleOf",
    "en": "Value must be a multiple of {{0}}",
    "ru": ""
  },
  {
    "id": "error_maximum_excl",
    "en": "Value must be less than {{0}}",
    "ru": ""
  },
  {
    "id": "error_maximum_incl",
    "en": "Value must be at most {{0}}",
    "ru": ""
  },
  {
    "id": "error_minimum_excl",
    "en": "Value must be greater than {{0}}",
    "ru": ""
  },
  {
    "id": "error_minimum_incl",
    "en": "Value must be at least {{0}}",
    "ru": ""
  },
  {
    "id": "error_maxLength",
    "en": "Value must be at most {{0}} characters long",
    "ru": ""
  },
  {
    "id": "error_minLength",
    "en": "Value must be at least {{0}} characters long",
    "ru": ""
  },
  {
    "id": "error_pattern",
    "en": "Value must match the pattern {{0}}",
    "ru": ""
  },
  {
    "id": "error_additionalItems",
    "en": "No additional items allowed in this array",
    "ru": ""
  },
  {
    "id": "error_maxItems",
    "en": "Value must have at most {{0}} items",
    "ru": ""
  },
  {
    "id": "error_minItems",
    "en": "Value must have at least {{0}} items",
    "ru": ""
  },
  {
    "id": "error_uniqueItems",
    "en": "Array must have unique items",
    "ru": ""
  },
  {
    "id": "error_maxProperties",
    "en": "Object must have at most {{0}} properties",
    "ru": ""
  },
  {
    "id": "error_minProperties",
    "en": "Object must have at least {{0}} properties",
    "ru": ""
  },
  {
    "id": "error_required",
    "en": "Object is missing the required property '{{0}}'",
    "ru": ""
  },
  {
    "id": "error_additional_properties",
    "en": "No additional properties allowed, but property {{0}} is set",
    "ru": ""
  },
  {
    "id": "error_dependency",
    "en": "Must have property {{0}}",
    "ru": ""
  },
  {
    "id": "button_delete_all",
    "en": "All",
    "ru": ""
  },
  {
    "id": "button_delete_all_title",
    "en": "Delete All",
    "ru": ""
  },
  {
    "id": "button_delete_last",
    "en": "Last {{0}}",
    "ru": ""
  },
  {
    "id": "button_delete_last_title",
    "en": "Delete Last {{0}}",
    "ru": ""
  },
  {
    "id": "button_add_row_title",
    "en": "Add {{0}}",
    "ru": ""
  },
  {
    "id": "button_move_down_title",
    "en": "Move down",
    "ru": ""
  },
  {
    "id": "button_move_up_title",
    "en": "Move up",
    "ru": ""
  },
  {
    "id": "button_delete_row_title",
    "en": "Delete {{0}}",
    "ru": ""
  },
  {
    "id": "button_delete_row_title_short",
    "en": "Delete",
    "ru": ""
  },
  {
    "id": "button_collapse",
    "en": "Collapse",
    "ru": ""
  },
  {
    "id": "button_expand",
    "en": "Expand",
    "ru": ""
  },
  {
    "id": "tbl_attr_modal_title",
    "en": "Attribute table",
    "ru": ""
  },
  {
    "id": "login_single_use_password_email",
    "en": "<div style=\"max-width:400px;padding:20px\">Hello,  <br><br> Here is the requested password:  <hr>  <span style=\"font-family:monospace;\">{{PASSWORD}}</span>  <hr> This secure password is valid only once, for the current MapX session and will be invalidated after 20 minutes.<br>Best regards,<br><br>Your MapX team.<br><br>  <span style=\"opacity:0.5;font-size:0.8em\">If you did not make this request, one of our user probably entered your email address by mistake.</span></div>",
    "ru": ""
  },
  {
    "id": "filter_views_list_mode_intersection",
    "en": "Intersection",
    "ru": ""
  },
  {
    "id": "filter_views_list_mode_union",
    "en": "Union",
    "ru": ""
  },
  {
    "id": "api_upload_file_max_size_exceeded_title",
    "en": "Maximum size reached",
    "ru": ""
  },
  {
    "id": "api_upload_file_max_size_exceeded",
    "en": "Maximum file size of {{size}} has been reached. You are not allowed to upload file greater than that. Please contact us for more information.",
    "ru": ""
  },
  {
    "id": "modal_check_confirm_project_change_txt",
    "en": "Are you sure to change project now ? Unsaved changes could be lost.",
    "ru": ""
  },
  {
    "id": "modal_check_confirm_project_change_btn",
    "en": "Change project now, discard changes.",
    "ru": ""
  },
  {
    "id": "modal_check_confirm_project_change_title",
    "en": "Change project confirmation",
    "ru": ""
  },
  {
    "id": "share_map_pos_set",
    "en": "Set map position",
    "ru": ""
  },
  {
    "id": "share_map_pos_get",
    "en": "Get current position",
    "ru": ""
  },
  {
    "id": "view_filter_no_items",
    "en": "Empty",
    "ru": ""
  },
  {
    "id": "share_manager_title",
    "en": "Sharing manager",
    "ru": ""
  },
  {
    "id": "share_link_title",
    "en": "Share link",
    "ru": ""
  },
  {
    "id": "share_options",
    "en": "Share options",
    "ru": ""
  },
  {
    "id": "share_mode_static_label",
    "en": "Use the mode 'static' ( recommended )",
    "ru": ""
  },
  {
    "id": "share_mode_static_desc",
    "en": "Use the 'static' mode if you want to share a view using a lightweight and faster version of MapX, with limited functionalities. Using this method, anyone with the shared link will be allowed to read the selected view, without the need of being registered in MapX. If you add a story map, it will start automatically, discarding any other views.",
    "ru": ""
  },
  {
    "id": "share_views_check_label",
    "en": "Add views to share",
    "ru": ""
  },
  {
    "id": "share_views_check_desc",
    "en": "Views to display. The list can be reordered : top views will have layers displayed on top. In 'static' mode, those views will be rendered automatically. Story maps will start directly. In 'normal' mode, the views will be displayed in the list and if the selection is empty, all views of the project will be listed.",
    "ru": ""
  },
  {
    "id": "share_views_zoom_label",
    "en": "Zoom to views extent",
    "ru": ""
  },
  {
    "id": "share_views_zoom_desc",
    "en": "In 'static' mode, this will set the map extent to fit views layers extent, if available.",
    "ru": ""
  },
  {
    "id": "share_views_open_check_label",
    "en": "Set views to activate",
    "ru": ""
  },
  {
    "id": "share_views_open_check_desc",
    "en": "Add views to be automatically activated when the application is launched. This will enable the button 'filter activate view' and hide non-activated view.",
    "ru": ""
  },
  {
    "id": "share_collections_check_label",
    "en": "Set collections",
    "ru": ""
  },
  {
    "id": "share_collections_check_operator_label",
    "en": "Selection mode (if more that one collection)",
    "ru": ""
  },
  {
    "id": "share_collections_check_operator_all",
    "en": "Intersection",
    "ru": ""
  },
  {
    "id": "share_collections_check_operator_any",
    "en": "Union",
    "ru": ""
  },
  {
    "id": "share_collections_check_desc",
    "en": "Add groups of views by using collections",
    "ru": ""
  },
  {
    "id": "share_map_pos_check_label",
    "en": "Set map position",
    "ru": ""
  },
  {
    "id": "share_map_pos_check_desc",
    "en": "Setting the position of the map will show a defined spatial extend instead of exposing a representation of the whole world.",
    "ru": ""
  },
  {
    "id": "share_iframe_check_label",
    "en": "Embed in HTML tags",
    "ru": ""
  },
  {
    "id": "share_iframe_check_desc",
    "en": "Embed the link in an <iframe> HTML tag to easily add MapX to your website.",
    "ru": ""
  },
  {
    "id": "share_in_project_title",
    "en": "Share in another project",
    "ru": ""
  },
  {
    "id": "share_in_project_desc",
    "en": "Share a view in a project where you have publisher rights",
    "ru": ""
  },
  {
    "id": "share_in_project_btn",
    "en": "Add in selected project",
    "ru": ""
  },
  {
    "id": "jenks",
    "en": "Jenks natural breaks",
    "ru": ""
  },
  {
    "id": "quantile",
    "en": "Quantile",
    "ru": ""
  },
  {
    "id": "head_tails",
    "en": "Head/tail Breaks",
    "ru": ""
  },
  {
    "id": "equal_interval",
    "en": "Equal interval",
    "ru": ""
  },
  {
    "id": "en",
    "en": "English",
    "ru": ""
  },
  {
    "id": "fr",
    "en": "French",
    "ru": ""
  },
  {
    "id": "es",
    "en": "Spanish",
    "ru": ""
  },
  {
    "id": "ru",
    "en": "Russian",
    "ru": ""
  },
  {
    "id": "zh",
    "en": "Chinese",
    "ru": ""
  },
  {
    "id": "de",
    "en": "German",
    "ru": ""
  },
  {
    "id": "bn",
    "en": "Bengali",
    "ru": ""
  },
  {
    "id": "fa",
    "en": "Farsi",
    "ru": ""
  },
  {
    "id": "ps",
    "en": "Pashto",
    "ru": ""
  }
]